Workbook

Sheet Literature summary
B1: The list | D1: Ingestion (text into the vault) | G1: Synthesis
A2: Area | B2: Sources | C2: Acquired | D2: Ingested | E2: % of sources | F2: Needs attention | G2: Synthesized | H2: % of sources
A3: Economic Activity | B3: =COUNTA('Qual - Economic Activity'!A:A)-1-COUNTIF('Qual - Economic Activity'!E:E,"Dropped") | C3: =COUNTIF('Qual - Economic Activity'!E:E,"Yes") | D3: =COUNTIF('Qual - Economic Activity'!K:K,"Ingested") | E3: =IF(B3=0,"",D3/B3) | F3: =COUNTIF('Qual - Economic Activity'!K:K,"Needs attention") | G3: =COUNTIF('Qual - Economic Activity'!O:O,"Yes") | H3: =IF(B3=0,"",G3/B3)
A4: Exchange Rate | B4: =COUNTA('Qual - Exchange Rate'!A:A)-1-COUNTIF('Qual - Exchange Rate'!E:E,"Dropped") | C4: =COUNTIF('Qual - Exchange Rate'!E:E,"Yes") | D4: =COUNTIF('Qual - Exchange Rate'!K:K,"Ingested") | E4: =IF(B4=0,"",D4/B4) | F4: =COUNTIF('Qual - Exchange Rate'!K:K,"Needs attention") | G4: =COUNTIF('Qual - Exchange Rate'!O:O,"Yes") | H4: =IF(B4=0,"",G4/B4)
A5: Fiscal Policy | B5: =COUNTA('Qual - Fiscal Policy'!A:A)-1-COUNTIF('Qual - Fiscal Policy'!E:E,"Dropped") | C5: =COUNTIF('Qual - Fiscal Policy'!E:E,"Yes") | D5: =COUNTIF('Qual - Fiscal Policy'!K:K,"Ingested") | E5: =IF(B5=0,"",D5/B5) | F5: =COUNTIF('Qual - Fiscal Policy'!K:K,"Needs attention") | G5: =COUNTIF('Qual - Fiscal Policy'!O:O,"Yes") | H5: =IF(B5=0,"",G5/B5)
A6: Inflation | B6: =COUNTA('Qual - Inflation'!A:A)-1-COUNTIF('Qual - Inflation'!E:E,"Dropped") | C6: =COUNTIF('Qual - Inflation'!E:E,"Yes") | D6: =COUNTIF('Qual - Inflation'!K:K,"Ingested") | E6: =IF(B6=0,"",D6/B6) | F6: =COUNTIF('Qual - Inflation'!K:K,"Needs attention") | G6: =COUNTIF('Qual - Inflation'!O:O,"Yes") | H6: =IF(B6=0,"",G6/B6)
A7: Labor Market | B7: =COUNTA('Qual - Labor Market'!A:A)-1-COUNTIF('Qual - Labor Market'!E:E,"Dropped") | C7: =COUNTIF('Qual - Labor Market'!E:E,"Yes") | D7: =COUNTIF('Qual - Labor Market'!K:K,"Ingested") | E7: =IF(B7=0,"",D7/B7) | F7: =COUNTIF('Qual - Labor Market'!K:K,"Needs attention") | G7: =COUNTIF('Qual - Labor Market'!O:O,"Yes") | H7: =IF(B7=0,"",G7/B7)
A8: Monetary Policy | B8: =COUNTA('Qual - Monetary Policy'!A:A)-1-COUNTIF('Qual - Monetary Policy'!E:E,"Dropped") | C8: =COUNTIF('Qual - Monetary Policy'!E:E,"Yes") | D8: =COUNTIF('Qual - Monetary Policy'!K:K,"Ingested") | E8: =IF(B8=0,"",D8/B8) | F8: =COUNTIF('Qual - Monetary Policy'!K:K,"Needs attention") | G8: =COUNTIF('Qual - Monetary Policy'!O:O,"Yes") | H8: =IF(B8=0,"",G8/B8)
A9: Trader | B9: =COUNTA('Qual - Trader'!A:A)-1-COUNTIF('Qual - Trader'!E:E,"Dropped") | C9: =COUNTIF('Qual - Trader'!E:E,"Yes") | D9: =COUNTIF('Qual - Trader'!K:K,"Ingested") | E9: =IF(B9=0,"",D9/B9) | F9: =COUNTIF('Qual - Trader'!K:K,"Needs attention") | G9: =COUNTIF('Qual - Trader'!O:O,"Yes") | H9: =IF(B9=0,"",G9/B9)
A10: Total | B10: =SUM(B3:B9) | C10: =SUM(C3:C9) | D10: =SUM(D3:D9) | E10: =IF(B10=0,"",D10/B10) | F10: =SUM(F3:F9) | G10: =SUM(G3:G9) | H10: =IF(B10=0,"",G10/B10)
A12: Sources: rows of the area tab, one per file (a book has a row per chapter), dropped rows excluded. Acquired: the PDF is in the folder. Ingested: its text is in the vault. Needs attention: ingestion was tried and the tools could not read it (a scan, a broken font — the reason is in the area tab). Synthesized: the ingested file has a synthesis note. Both % columns divide by Sources.
A13: Acquired but neither Ingested nor Needs attention: not run yet (/ingest), or the area is on hold in settings.yaml (Trader). Recurring BCB documents (Copom statement, minutes, RPM) reach the vault through the Copom ETL and have no row here.
A14: The reasoning behind each area's list — scope, cluster notes, open gaps, acquisition order — is in the Notes tab.
A15: Written by repository/ingestion/scripts/tracker.py on every ingestion. In the area tabs, teal columns are yours, navy ones the system's.

Sheet Notes
A1: Area | B1: Kind | C1: Cluster / section | D1: What it covers | E1: Notes
A2: Exchange Rate | B2: Literature | C2: (whole area) | D2: Scope | E2: Excluded here: #pass_through_and_inflation. That cluster sits at a genuine intersection between this exchange-rate bibliography and the inflation agent's own bibliography (the Qual - Inflation tab) — which side of that boundary owns exchange-rate pass-through hasn't been decided yet, the same kind of explicit scope call other topics in this series have had to make (e.g. fiscal policy vs. monetary policy on fiscal dominance, in the Qual - Fiscal Policy tab). Goldfajn & Werlang (2000), Belaisch (2003), and Araújo/Caldarelli/Cortapasso (2023) remain exactly where they are in exchange_rate_conceptual_map.md and repository/exchange_rate/ — only removed from this consolidated list pending that ownership decision.
A3: Exchange Rate | B3: Literature | C3: (whole area) | D3: Where the base is strong (multiple independent sources converge) | E3: - Interest-rate/exchange-rate parity conditions (UIP, CIP, real interest parity, international Fisher effect) — covered from five independent angles (CFA L1/L2, Krugman Ch. 14/16, Dornbusch, and now Fama's 1984 original econometric source) that consistently cross-reference and refine each other. This is the single best-supported cluster in the base, and now includes the actual academic origin of the "wrong-signed beta"/forward-premium-puzzle result the other sources describe narratively. - Exchange-rate pass-through, with a genuine Brazil specialization — five sources (Goldfajn 2000, Belaisch 2003, Krugman Ch. 17's Marshall-Lerner/J-curve, Cortapasso et al. 2023, and the BCB note) build a coherent, empirically-grounded, Brazil-specific picture: aggregate pass-through → distribution-chain detail → formal elasticity conditions → state-dependent/asymmetric refinement → market-plumbing detail. This is arguably the base's most distinctive strength relative to a generic textbook treatment, and directly serves LIS's Brazil macro mandate. - Fixed-rate mechanics and currency crises — now the base's deepest cluster after the 2026-07 addition of five academic crisis-model papers (sources 19-23). The operational "how a peg is actually defended, and how it breaks" story (Mundell 1963 → Krugman Ch. 18 → CFA L2's warning-sign checklist → four case studies: Malaysia, Iceland, Switzerland, Brazil 2002-2011) is now backed by the full academic theoretical spine it previously lacked: the original first-generation model and its linear/stochastic companion (Krugman 1979; Flood & Garber 1983/84), the original second-generation self-fulfilling model (Obstfeld 1984), and both major competing third-generation models (Krugman's balance-sheet/transfer-problem model, 2000; Chang & Velasco's open-economy bank-run model, 1998) — including their own direct debate with each other over which mechanism actually drove the 1997-98 Asian crisis. Includes a strong-currency defense (Switzerland), a non-crisis cautionary tale (Brazil), and now a first-hand methodological self-critique (Garber's "generational taxonomy is a name swindle" comment) — a genuinely well-rounded, non-one-note treatment of the topic. - Equilibrium/fair-value estimation (BEER/GSDEER/GSFEER) — the two major methodological families (academic BEER, practitioner GSDEER, and now GSFEER) are all present with enough detail to compare their assumptions, failure modes, and current live signals for BRL specifically. - Capital controls as a policy tool — no longer a single-source cluster after the 2026-07 addition of both the empirical precursor (Ostry et al., 2010) and the IMF's own official institutional doctrine (2012 Board paper). Together with the case-study material already in #currency_crisis_dynamics/#balance_of_payments, the base now covers the full arc: when controls are justified (four-condition test), how effective they actually are (composition vs. volume effects, the 2008-09 natural experiment), the CFM/MPM terminology distinction, liberalization sequencing, and the multilateral-spillover case against unilateral overuse. - Currency regime choice, from first principles — Mundell's 1961 OCA paper (added 2026-07) now sits alongside his 1963 capital-mobility paper, giving the base both halves of Mundell's own regime-choice framework: which geographic unit should share a currency (1961) and what a shared/fixed currency costs in terms of monetary independence (1963) — directly relevant to any EMU-style or dollarization-adjacent regime analysis. - Political economy of exchange rate policy — no longer a narrative-only gap after the addition of Frieden (1991), the canonical sectoral-interests paper. The base now has a genuine theoretical answer to "who wins and loses, domestically, from a given exchange-rate regime or level" — directly deepening the previously narrative-only Cortapasso et al. discussion of Brazilian political-currency dynamics.
A4: Exchange Rate | B4: Literature | C4: (whole area) | D4: Where the base is thin (single source, or gaps entirely) | E4: - Gaps not represented in the base at all (see the Qual - Exchange Rate tab for concrete candidate sources and priority order): - FX options and volatility — forwards, swaps, and futures are covered; option pricing, implied vol surfaces, and risk-reversal/skew as an FX positioning indicator are not. - China/RMB, or any large non-Brazil EM case study — the EM material in this base is almost entirely Brazil-specific; there's no equivalent depth for, say, RMB internationalization/managed float mechanics, or the "original sin" (EM local-currency debt market) literature. - Brazil-specific capital controls empirics (Chamon & Garcia's 2016 IOF-tax study) — the base now has the general institutional-view framework but not a dedicated empirical test on Brazil's own 2008-2012 episode; a natural next addition given the base's Brazil mandate. - The other two classic OCA papers (McKinnon 1963, Kenen 1969) — Mundell's OCA paper is now in the base, but the trio that forms the standard OCA canon isn't complete.
A5: Exchange Rate | B5: Literature | C5: (whole area) | D5: Which data backs which cluster (folded in 2026-09-10) | E5: Reading the map from the data side instead of the literature side gives three findings the cluster-by-cluster bullets don't show on their own: - Two data categories carry most of the base. Carry/rate differential (§2) and reserves/intervention (§6) each connect to four clusters — determination, valuation, crisis dynamics or regimes, and the practitioner layer. They are cited from the most distinct theoretical angles, so a defect in either propagates furthest. - One cluster connects to nothing: #policy_transmission (see the note in its own section). Eight of nine clusters have at least one series behind them; the ninth is the base's most political-economy-flavoured, and nothing in the pipeline measures it. - A single series usually needs more than one lens. Terms of trade (§3) and positioning (§8) each feed three clusters spanning both the academic literature and the Verde practitioner layer — a reminder that reading either through one theory at a time is a choice, not a default. And two gaps turn out to be the same gap seen from two sides, which is the argument for keeping the two layers in one file: FX options have neither a series (§8) nor a source (Garman-Kohlhagen), and non-Brazil EM depth has neither the REER peers (§7) nor the literature (Eichengreen & Hausmann). Closing one half of either would leave the other half still open.
A6: Exchange Rate | B6: Literature | C6: (whole area) | D6: One-paragraph overview (for board use) | E6: The exchange-rate bibliography covers the full standard arc of international-finance theory — from FX market mechanics and quoting conventions, through the interest-rate-parity/PPP family that links currencies to interest rates and inflation (now including the original UIP-failure econometrics, Fama 1984), to the two workhorse short-run models (Mundell-Fleming policy transmission and Dornbusch overshooting) and their long-run monetary counterparts — and grounds all of it in practitioner tools actually used to value currencies today (BEER, GSDEER, GSFEER) plus a now-comprehensive, multi-generational treatment of how currency crises build and break, spanning the field's original academic models (Krugman 1979, Flood & Garber, Obstfeld 1984) through both competing third-generation accounts of the Asian crisis (Krugman 2000, Chang & Velasco 1998). It also now covers currency-regime choice from first principles (Mundell's OCA theory), capital-flow management as an official policy doctrine (the IMF's institutional view and its empirical precursor), and the political economy of exchange-rate policy (Frieden's sectoral-interests framework). Its standout strengths are a genuinely deep, Brazil-specific thread on exchange-rate pass-through and BCB market operations, and an equally deep academic-theory-plus-case-study treatment of currency crisis dynamics and capital account policy. Its main remaining gaps are FX options/volatility and comparative EM depth beyond Brazil.
A7: Exchange Rate | B7: Literature | C7: #market_microstructure | D7: FX market structure, quoting, and plumbing
A8: Exchange Rate | B8: Literature | C8: #exchange_rate_determination | D8: nominal, real, and equilibrium exchange rates
A9: Exchange Rate | B9: Literature | C9: #currency_regimes | D9: regime choice, OCA theory, and the trilemma
A10: Exchange Rate | B10: Literature | C10: #balance_of_payments | D10: trade, capital flows, and the accounting identities | E10: No open gaps currently flagged for this cluster — the accounting-identity spine is well covered; deeper empirical BOP-crisis material sits under #currency_crisis_dynamics instead.
A11: Exchange Rate | B11: Literature | C11: #policy_transmission | D11: monetary & fiscal policy under different regimes, and its politics
A12: Exchange Rate | B12: Literature | C12: #applied_valuation_tools | D12: estimating the "equilibrium" exchange rate
A13: Exchange Rate | B13: Literature | C13: #capital_controls | D13: restrictions on capital flows as a policy tool
A14: Exchange Rate | B14: Literature | C14: #currency_crisis_dynamics | D14: how currency crises build and break
A15: Exchange Rate | B15: Literature | C15: #practitioner_mental_models | D15: how specific macro funds actually reason about BRL/USD | E15: Distinct in kind from clusters 1–8, not just in number. These are internally-authored syntheses of how specific macro funds actually reason about BRL/USD and the global dollar cycle, extracted from their own letters/notes rather than from published academic or institutional literature — a practitioner-reasoning cluster sitting alongside, not graded on the same foundational-score scale as, the literature above (hence the different table columns below).
A16: Exchange Rate | B16: Literature | C16: (whole area) | D16: 3. Optimal Currency Area (OCA) theory — absent entirely — PARTIALLY RESOLVED 2026-07 | E16: Only Mundell's 1963 capital-mobility paper was in the base; his more famous 1961 OCA paper was missing, along with the other two "classic" OCA criteria papers.
A17: Exchange Rate | B17: Literature | C17: (whole area) | D17: 4. FX options and volatility — absent entirely | E17: Forwards, swaps, and futures are covered (via CFA L1 and the BIS Triennial Survey figures); options pricing and volatility-based positioning indicators are not.
A18: Exchange Rate | B18: Literature | C18: (whole area) | D18: 6. Non-Brazil EM depth (RMB internationalization, "original sin") — almost entirely absent | E18: Every EM-specific source in the base is Brazil-focused. No equivalent depth for China/RMB or the broader EM local-currency-debt literature.
A19: Exchange Rate | B19: Literature | C19: (whole area) | D19: Suggested acquisition order | E19: 1. Chamon & Garcia (2016) (Section 2, Brazil angle) — a natural, low-effort next step given the base's Brazil mandate and the fact that the general capital-controls framework is now in place; this would be the direct empirical application to Brazil's own 2008-2012 IOF episode. 2. Garman & Kohlhagen (1983) (Section 4) — closes the one theory area (FX options/volatility) with no representation at all in the base. Everything else can follow based on what LIS's near-term research agenda actually needs (e.g., the remaining OCA companions only matter if EMU/monetary-union analysis is on the roadmap; RMB depth only matters if non-Brazil EM work is planned).
A20: Monetary Policy | B20: Literature | C20: (whole area) | D20: Scope | E20: Scope: technical literature only (papers, handbook chapters, selected textbook chapters). The Copom's own documents (comunicados, atas, RPM) are a separate track — §8 of the candidates file — already in obsidian/monetary_policy/clean_md/central_bank/, refreshed by the Copom ETL, and not listed here.
A21: Monetary Policy | B21: Literature | C21: (whole area) | D21: What the agent has to answer, and which clusters answer it | E21: The review that produced clusters 9-13 started from the agent's job rather than from the field's table of contents. The memo horizons are the next meeting, year-end, 1 year and 2-3 years (SISTEMA_AGENTES.md I.III), and the exchange-rate map already asks the agent for four outputs: Clusters 1-3 and 5 are the theoretical floor under all of these. Before 2026-10-07 the base was strong there and thin on every row of the table above; the Brazil cluster stopped in 2006.
A22: Monetary Policy | B22: Literature | C22: (whole area) | D22: Primary legal sources (institutional framework) | E22: Not literature, and therefore outside the clusters, but they define the target the reaction function responds to. Same treatment as the legal sources in the fiscal bibliography.
A23: Monetary Policy | B23: Literature | C23: (whole area) | D23: Deliberately out of this list | E23: - Woodford (2003) Interest and Prices, Cukierman (1992) and Bernanke, Laubach, Mishkin & Posen (1999) — the three books the candidates file used to carry. Their content for this agent is already covered: Woodford by Galí and Clarida-Galí-Gertler, Cukierman by Rogoff, Walsh and Barro-Gordon, Bernanke et al. by Svensson, Mishkin and the Brazil papers. Dropped 2026-10-07. - Phillips curve, expectation formation, fiscal theory of the price level, output-gap filters — owned by the inflation, fiscal and activity bibliographies. Expectations are not this agent's (SISTEMA_AGENTES.md I.III.xii); duplicating them here would blur the agents. </content>
A24: Monetary Policy | B24: Literature | C24: #policy_rules_and_credibility | D24: rules vs. discretion, time inconsistency, institutional design
A25: Monetary Policy | B25: Literature | C25: #new_keynesian_transmission | D25: the modern theoretical backbone
A26: Monetary Policy | B26: Literature | C26: #transmission_channels_financial_frictions | E26: Answers: How, and how fast, does the Selic reach activity and inflation in Brazil?
A27: Monetary Policy | B27: Literature | C27: #unconventional_policy_zlb | E27: Lowest processing priority of the base: Brazil came near the floor only in 2020.
A28: Monetary Policy | B28: Literature | C28: #global_spillovers_em_autonomy | E28: Answers: S4 — reaction function to a depreciation, and with which instrument
A29: Monetary Policy | B29: Literature | C29: #brazil_monetary_policy | E29: Answers: How, and how fast, does the Selic reach activity and inflation in Brazil? Answers: How restrictive is the Selic today? Answers: S2 — is a hike read as credibility or as validation of higher inflation? The 2006 cutoff is partly closed. The open gap this cluster carried — nothing after 2006 — is now covered on transmission (Minella & Souza-Sobrinho 2013, Bonomo & Martins 2016), the FX reaction (Kohlscheen 2014) and the BCB's model (SAMBA). Still uncovered by technical literature: the 2015-16 recession and the 2021-23 cycle. For those, the Copom's own documents (§8) and the technical boxes of the RPM — which come with the full RPM history, SISTEMA_AGENTES.md II.III.iv — are the primary source, not a paper still to be found.
A30: Monetary Policy | B30: Literature | C30: #reaction_function_and_gradualism | D30: estimating what the central bank responds to, and how fast | E30: Answers: S4 — reaction function to a depreciation, and with which instrument Answers: S1 — expected Selic path and balance of risks; how far it sits from the curve and from the Focus
A31: Monetary Policy | B31: Literature | C31: #policy_surprises_and_information_effect | D31: what a decision tells the market | E31: Answers: S2 — is a hike read as credibility or as validation of higher inflation?
A32: Monetary Policy | B32: Literature | C32: #communication_and_forward_guidance | E32: Answers: S3 — how the Copom described the exchange rate
A33: Monetary Policy | B33: Literature | C33: #neutral_rate | D33: how restrictive is the policy rate? | E33: Answers: How restrictive is the Selic today? Answers: S1 — expected Selic path and balance of risks; how far it sits from the curve and from the Focus
A34: Monetary Policy | B34: Literature | C34: #term_structure_and_market_pricing | D34: separating the expected path from the premium | E34: Answers: S1 — expected Selic path and balance of risks; how far it sits from the curve and from the Focus
A35: Monetary Policy | B35: Literature | C35: (whole area) | D35: Acquisition note | E35: The IMF blocks automated download. imf.org returns 403 to scripted requests (Akamai), for both the /external/pubs/ft/wp/ and the /-/media/ paths, from curl and from PowerShell alike (tested 2026-10-07). The papers themselves are free — open the link in a browser, save the PDF into repository/monetary_policy/raw_pdf/ with the suggested filename, and run /ingest monetary_policy. Third-party mirrors were not used.
A36: Monetary Policy | B36: Literature | C36: #brazil_policy_communication | D36: Copom primary sources | E36: A recurring institutional feed, not settled literature; no foundational score. The two decisions this section used to defer are taken: retention is the full history for comunicados (234) and atas (261), and the RPM for the last three years in full (12, Dec/2023 on); ingestion is the Copom ETL (pm_copom_projecoes.run(), code in domain/db/brasil/bcb/_copom_texto.py and _rpm_projecoes.py), writing straight into obsidian/monetary_policy/clean_md/central_bank/. Still pending: the full RPM history (SISTEMA_AGENTES.md II.III.iv).
A37: Economic Activity | B37: Literature | C37: (whole area) | D37: Scope | E37: Scope — deliberately excludes labor market theory. The user is considering splitting labor market into its own future agent, separate from economic activity. This file covers the business cycle and growth side only: what drives aggregate output up and down over the short run (business cycle theory), what drives it higher over the long run (growth theory), how "how much slack is there" gets measured (output gap/potential output), and how Brazil's own activity is tracked and dated. It deliberately does not cover search/matching models, the Beveridge curve, or NAIRU estimation — those stay reserved for the future labor market agent, even though output gap and NAIRU are close conceptual cousins. Scope boundary with the Qual - Monetary Policy tab: monetary policy's #new_keynesian_transmission and #transmission_channels_financial_frictions clusters already own the monetary transmission mechanism (Calvo pricing, the credit channel, the financial accelerator) — this file covers business cycles from the real/output side (RBC theory, growth theory) rather than how monetary policy transmits into them. Cluster 2 below (#modern_dsge_business_cycles) is the one place the two files sit closest together — Smets & Wouters (2007) and the CEE (2005) model are joint output-inflation-policy frameworks — included here because the lens is business-cycle propagation, not the policy-rule side already covered in monetary policy's bibliography. Scope boundary with the Qual - Inflation tab: Phillips curve theory and estimation (the use of the output gap as a slack measure) stays in the inflation file's cluster 1 — this file owns the theory and measurement of the output gap itself, which the inflation and monetary policy agents both already list as a Tier 2 dependency they need from a future activity agent. Scope boundary with exchange_rate_policy/ and inflation's cost-push cluster: commodity-price pass-through to consumer prices stays with inflation (cluster 3); this file's commodity cluster (8) covers the structural growth/Dutch-disease channel — how a commodity cycle reshapes potential output and industrial competitiveness — not the price-transmission channel.
A38: Economic Activity | B38: Literature | C38: (whole area) | D38: Suggested acquisition order | E38: 1. Okun (1962) and Cusinato, Minella & Pôrto Júnior (2010) — cheapest high-value pair: one closes the conceptual foundation for "output gap," the other is the single most load-bearing Brazil-specific reference, directly answering a gap already flagged in the monetary policy data inventory. 2. Solow (1956) and Kydland & Prescott (1982) — the two single most-cited papers in this entire bibliography; nothing else here makes full sense without these two frameworks (long-run growth, short-run real cycles) as background. 3. Banco Central do Brasil (2010, 2016, 2018) IBC-Br boxes — read together as a set; they're short, and the methodology only makes sense read as a sequence (launch → revision → comparison-to-GDP). 4. Corden & Neary (1982) — closes the Dutch disease gap cheaply; short, frequently invoked in Brazilian industrial-policy commentary, worth having early. 5. Solow (1957), Banco Central do Brasil (2018), Estudo Especial nº 27, and Veloso, Matos & Peruchetti (2020a/b) — the full productivity set; read the growth-accounting theory first, then BCB's labor-productivity-only application, then FGV/IBRE's fuller aggregate-TFP series, so the progression from theory → partial Brazilian application → complete Brazilian application is visible. 6. Duarte, Issler & Spacov (2004) — read alongside Burns & Mitchell and Stock & Watson (cluster 1/6) once those are acquired, since it's the direct Brazilian application of both. 7. Everything else, roughly in cluster order — the Barro & Sala-i-Martin (2004) textbook chapters, the IBGE national accounts methodology note, and the two 2019-2020 BCB Estudos Especiais (uncertainty, financial conditions) are lower urgency, useful thickening rather than foundational.
A39: Economic Activity | B39: Literature | C39: #business_cycle_theory_foundations | D39: the impulse-propagation framework and its two founding schools
A40: Economic Activity | B40: Literature | C40: #modern_dsge_business_cycles | D40: the medium-scale estimated models central banks actually run
A41: Economic Activity | B41: Literature | C41: #growth_theory_neoclassical_and_endogenous | D41: what drives output higher over the long run
A42: Economic Activity | B42: Literature | C42: #convergence_middle_income_trap_and_em_growth | D42: does growth converge, and why Brazil's own growth has repeatedly stalled
A43: Economic Activity | B43: Literature | C43: #output_gap_and_potential_output_measurement | D43: how "how much slack is there" actually gets estimated
A44: Economic Activity | B44: Literature | C44: #business_cycle_dating_and_coincident_indicators | D44: turning many series into one cycle signal, and dating its turning points | E44: Ongoing primary source, not a single paper: Comitê de Datação de Ciclos Econômicos (CODACE), maintained by FGV/IBRE — Brazil's own NBER-style business cycle dating committee, publishing recession/expansion turning-point calls and methodology notes on an ongoing basis rather than a fixed calendar (unlike COPOM's ~8/year cadence in the monetary policy bibliography's §8). Retention window and ingestion approach not yet decided — flagged here rather than left undocumented, following the precedent set for COPOM materials.
A45: Economic Activity | B45: Literature | C45: #brazil_activity_measurement | D45: IBC-Br and the national accounts it approximates
A46: Economic Activity | B46: Literature | C46: #commodity_cycles_dutch_disease_and_growth | D46: the structural growth channel of Brazil's commodity exposure | E46: Scope note: covers the growth/industrial-structure channel only — commodity price pass-through into consumer prices is inflation's territory (cluster 3 there); this cluster is about how a commodity cycle reshapes potential output and competitiveness.
A47: Economic Activity | B47: Literature | C47: #brazil_productivity_and_potential_growth | D47: measuring productivity itself, not just the output gap it feeds into | E47: Distinct from cluster 5: cluster 5 covers output gap measurement (actual output vs. potential, cyclical); this cluster covers productivity directly — the growth-accounting decomposition of potential output itself into capital, labor, and the residual (total factor productivity), which is the slower-moving trend cluster 5's methods are trying to extract in the first place. Ongoing primary source, not a single paper: the Observatório da Produtividade Regis Bonelli (ibre.fgv.br/observatorio-produtividade), FGV/IBRE's dedicated productivity-tracking portal — publishes the annual TFP and labor-productivity series above on an ongoing basis, plus further reports/notes (e.g. Veloso, Matos & Peruchetti's companion piece specifically on labor productivity as the long-run growth engine). Treat similarly to CODACE in cluster 6: an ongoing feed to monitor, not a one-time acquisition. Noted but not yet verified: both 2020 notes above cite an earlier survey, Veloso et al. (2013), reviewing the several competing Brazilian TFP estimates that predated this IBRE series — worth tracking down and adding if a fuller historical/comparative view of Brazilian TFP methodologies is wanted, but exact venue/co-authors weren't confirmed in this pass.
A48: Fiscal Policy | B48: Literature | C48: (whole area) | D48: Scope | E48: Scope — deliberately does not re-acquire fiscal-monetary interaction theory already covered elsewhere. Two other files already own significant fiscal-adjacent ground: Scope boundary with the Qual - Economic Activity tab: fiscal multipliers (cluster 2) are the one place this file and business-cycle theory sit closest together — multiplier size is state-dependent on the output gap (Auerbach & Gorodnichenko 2012) — but this file owns the fiscal-shock-identification side, while economic activity owns the output-gap measurement the multiplier size depends on.
A49: Fiscal Policy | B49: Literature | C49: (whole area) | D49: Suggested acquisition order | E49: 1. Domar (1944) and Blanchard (2019) — the debt-sustainability-arithmetic pair; read together since Blanchard's whole argument is a modern re-litigation of exactly the r-vs-g comparison Domar first formalized. 2. Lei Complementar 101/2000 (LRF), EC 95/2016 (Teto de Gastos), and LC 200/2023 (Novo Arcabouço Fiscal) — read as a sequence; Brazil's fiscal-rule history only makes sense read chronologically as one rule replacing the last. 3. Reinhart, Rogoff & Savastano (2003) — cheap, short (relative to a full book), and the single most important corrective to naively applying Blanchard (2019)'s DM-focused r-vs-g comfort to an EM context. 4. Blanchard & Perotti (2002) — closes the fiscal-multiplier methodology gap before either Ramey's survey or Auerbach-Gorodnichenko's state-dependence result will make full sense. 5. Gavin & Perotti (1997) — read alongside Reinhart-Rogoff-Savastano (2003) above; procyclicality and debt intolerance are the two empirical regularities most responsible for why EM/Latin American fiscal policy doesn't behave like the Domar/Blanchard (2019) arithmetic, calibrated against reserve-currency issuers, would predict. 6. Everything else, roughly in cluster order — the Barr & Diamond (2009), Oates (1972)/Rodden (2006), and Klemm (n.d.) book/chapter items are lower urgency, useful depth rather than foundational; the four flagged open gaps (Novo Arcabouço's peer-reviewed assessment, EC 103/2019's ex-post fiscal impact, Brazil's specific 2015-16/subnational crisis narratives, and a cleanly-citable Latin America subnational federalism paper) need a dedicated search pass before anything can be acquired against them.
A50: Fiscal Policy | B50: Literature | C50: #public_debt_sustainability_and_dynamics | D50: the arithmetic of whether debt is sustainable, and when it stops mattering
A51: Fiscal Policy | B51: Literature | C51: #fiscal_multipliers | D51: how much a real of spending or a real of tax cut actually moves output
A52: Fiscal Policy | B52: Literature | C52: #fiscal_rules_and_institutions | D52: designing constraints that bind, and Brazil's own attempts
A53: Fiscal Policy | B53: Literature | C53: #fiscal_capacity_debt_intolerance_and_dominance | D53: why EM sovereigns hit fiscal limits at debt levels DM sovereigns don't | E53: Distinct from, not a duplicate of, the FTPL/fiscal-dominance theory already in the Qual - Inflation tab cluster 7 and the applied Brazil pair in the Qual - Monetary Policy tab cluster 7 — this cluster's lens is fiscal capacity itself: why the same debt-to-GDP ratio that's unremarkable for a reserve-currency issuer can trigger a crisis for an emerging market. Open gap, not yet filled: the historical companion literature on Brazil's own specific debt-intolerance/fiscal-dominance episodes (the 2002 election-driven confidence crisis already covered from the exchange-rate/credibility angle in the Qual - Monetary Policy tab cluster 7's Minella et al. 2003, and the 2015-16 crisis, cluster 7 below) is the applied complement this theoretical paper needs — flagged here rather than duplicated.
A54: Fiscal Policy | B54: Literature | C54: #pension_and_social_security_reform | D54: the single largest, most persistent fiscal pressure | E54: Brazil relevance note: pension/social-security spending is the dominant driver of Brazil's structural primary-spending growth, and the minimum wage's role as the pension-benefit indexation floor (already flagged from the labor market side in the Qual - Labor Market tab cluster 6) means this cluster is unusually tightly linked to that agent's own material. Open gap, not yet filled: a dedicated ex-post economics (not legal-studies) assessment of EC 103/2019's actual realized fiscal savings, several years post-implementation, was not confidently identified in this pass — most search results were law-journal treatments of specific benefit categories rather than aggregate fiscal-impact studies. Flagged for a dedicated search pass, likely at IPEA, BCB, or the Tesouro Nacional's own long-term debt-projection notes.
A55: Fiscal Policy | B55: Literature | C55: #brazil_fiscal_federalism_and_subnational_debt | D55: where a large share of Brazil's fiscal risk actually sits | E55: Open gap, not yet filled: a dedicated Brazil-specific account of the 1990s state-debt crises and the LRF's origin as a direct institutional response (rather than the general cross-country treatment Rodden provides), and a dedicated account of Rio de Janeiro's 2016-17 fiscal crisis (RJ's own "regime de recuperação fiscal") specifically — neither was confidently identified with a specific citation in this pass; flagged for a dedicated search.
A56: Fiscal Policy | B56: Literature | C56: #brazil_fiscal_history_and_recent_episodes | D56: reading the fiscal stance narrative Brazil has actually lived through | E56: Structurally different from the other clusters, similar to how COPOM communications (monetary policy §8) and CODACE (economic activity §6) are treated: this is a placeholder for primary-source and applied-narrative material documenting specific fiscal episodes, not settled theory — flagged here so the gap is visible rather than silently absent. Open gaps, none filled yet with a specific citation: - The 2015-16 fiscal crisis, including the "pedaladas fiscais" (delayed transfers to public banks that were later ruled to constitute disguised fiscal borrowing, central to the 2016 impeachment proceedings) — a defining recent episode with no citation yet identified. - The COVID-19 fiscal response ("orçamento de guerra," the constitutional war-budget carve-out from the spending cap, and the Auxílio Emergencial cash-transfer program) and its aftermath for the post-2022 fiscal debate that led directly to cluster 3's Novo Arcabouço Fiscal — no specific citation yet identified.
A57: Fiscal Policy | B57: Literature | C57: #latin_america_regional_fiscal_policy | D57: Brazil as one case within a recurring regional pattern | E57: Added after the user's request to broaden beyond Brazil specifically to Latin America — mainstream empirical/institutional literature only (NBER, IMF), not the region's separate structuralist/heterodox tradition, consistent with this bibliography's general orientation. Open gap, not yet filled: a dedicated, cleanly-citable paper on Latin American subnational fiscal federalism specifically (as opposed to Rodden 2006's broader cross-country treatment in cluster 6, which includes but isn't limited to the region) was searched for but not confidently identified — the clearest candidate found (Ter-Minassian, Albino-War & Singh, 2004, "Managing Subnational Borrowing") is an unpublished conference paper without a stable formal citation, so it wasn't added; flagged for a follow-up search if a published version or a cleaner substitute is wanted.
A58: Inflation | B58: Literature | C58: (whole area) | D58: Scope | E58: Scope and boundary with the Qual - Monetary Policy tab: the two agents split the same broad territory by lens, not by keyword — inflation targeting as an institutional regime (rules, credibility, central bank design, the NK 3-equation transmission mechanism) stays in monetary policy; this file covers the inflation process itself — what actually drives the price level and its rate of change, how expectations form, how shocks propagate and get measured, and how disinflation has actually happened (or failed to) in Brazil and elsewhere. Where a classic source is genuinely foundational to both (Friedman 1968 was acquired first under monetary policy), it is cross-referenced here rather than re-acquired — see the note under cluster 1.
A59: Inflation | B59: Literature | C59: (whole area) | D59: Suggested acquisition order | E59: 1. Arida & Resende (1985) and Franco (1995) — the two-paper core of Brazil's original theoretical contribution and its main practical application; nothing else in this bibliography is as distinctively Brazil-specific or as directly load-bearing for explaining the Real Plan to a reader. 2. da Gama Machado (2024) and Bryan & Cecchetti (1994) — closes the measurement-methodology gap with both the general theory and BCB's own current, operative núcleo methodology; read together since the 2024 paper only makes sense against the trimmed-mean logic the 1994 paper establishes. 3. Gali & Gertler (1999) and Coibion & Gorodnichenko (2015), then Alves & Areosa (2005) and da Gama Machado & Portugal (2014) — the international NKPC pair followed immediately by their two Brazilian empirical counterparts, so the general theory is fresh when reading the local estimates. 4. Ball, Leigh & Mishkin (2022) and Bernanke & Blanchard (2023) — most likely to be immediately useful for current LIS analysis given the recency of the episode they cover. 5. Bevilaqua, Mesquita & Minella (2007) and Gaglianone (2017) — the two Brazil-specific expectations-anchoring references, read after cluster 2's international theory (Mankiw & Reis, Sims, Coibion-Gorodnichenko-Kamdar) rather than before it. 6. Everything else, roughly in cluster order — the Ha/Kose/Ohnsorge (2019) book chapters, Figueiredo & Fachada (2002) (now superseded by da Gama Machado 2024 but still useful as a historical baseline), and Areosa (2016) are lower urgency.
A60: Inflation | B60: Literature | C60: #phillips_curve_and_expectations_augmentation | D60: the core theoretical relationship between slack and inflation | E60: Cross-reference, not re-acquired: Friedman, M. (1968), "The Role of Monetary Policy," American Economic Review — already acquired under monetary_policy/ (the natural rate hypothesis is this cluster's other founding half alongside Phelps 1967); treat it as shared infrastructure rather than duplicating the PDF.
A61: Inflation | B61: Literature | C61: #inflation_expectations_formation_and_anchoring | D61: how expectations are actually formed, measured, and (de)anchored
A62: Inflation | B62: Literature | C62: #cost_push_shocks_and_exchange_rate_pass_through | D62: supply-side and imported inflation | E62: Scope note: exchange-rate-driven inflation is covered here strictly from the inflation-transmission side (how much of a depreciation shows up in consumer prices, and how fast); the currency-regime and UIP side of exchange rate economics stays in exchange_rate_policy/.
A63: Inflation | B63: Literature | C63: #brazilian_inertial_inflation_theory | D63: Brazil's own original contribution to inflation theory | E63: Why this cluster exists on its own: unlike most of this bibliography, inertial inflation theory was developed by Brazilian economists to explain a phenomenon (chronic indexation-driven inflation with no clear demand or supply trigger) that mainstream imported theory did not handle well — it is one of the few cases where Brazilian applied macro produced genuinely original theory rather than a local application of a foreign model.
A64: Inflation | B64: Literature | C64: #real_plan_disinflation | D64: Brazil's successful 1994 stabilization
A65: Inflation | B65: Literature | C65: #inflation_measurement_and_core_measures | D65: headline vs. core, and how "core" itself is constructed and forecast
A66: Inflation | B66: Literature | C66: #fiscal_theory_of_the_price_level | D66: inflation as a fiscal, not only monetary, phenomenon | E66: Bridges to, but is theoretically distinct from, monetary policy's #brazil_monetary_policy cluster (Blanchard 2004, Favero & Giavazzi 2004 on fiscal dominance) — those are applied Brazil pieces; this cluster is the underlying formal theory of price-level determination under fiscal constraints.
A67: Inflation | B67: Literature | C67: #post_pandemic_inflation_surge | D67: the 2021-23 global inflation shock and its ongoing reassessment | E67: Open gap, not yet filled: this cluster is entirely international (US-focused); no source yet specifically decomposes Brazil's 2021-23 inflation surge (which had its own distinctive drivers — the 2021 drought/energy shock, BRL depreciation, and a faster BCB hiking response than most DM peers). No specific citation is proposed since a confident title wasn't identifiable from memory — flag for a dedicated search pass, likely a BCB working paper or an IMF Article IV background note.
A68: Labor Market | B68: Literature | C68: (whole area) | D68: Scope | E68: Scope — the split confirmed in the Qual - Economic Activity tab. That file explicitly reserved search/matching models, the Beveridge curve, and NAIRU estimation for this agent, in exchange for keeping business-cycle theory and growth theory on the activity side. This file owns: how unemployment and vacancies coexist and interact (search/matching theory, the Beveridge curve), how wages get set (bargaining, the wage curve, minimum wage), what "full employment" even means (NAIRU/natural rate), and — because it is unusually consequential for Brazil specifically — informality and dual labor markets. Scope boundary with the Qual - Inflation tab: the Phillips curve itself (the price side of the slack-inflation relationship, its estimation, the missing-inflation/disinflation debates) stays in inflation's cluster 1 — this file owns the labor market mechanics that feed into it (unemployment gap, NAIRU, wage-setting), the same division already established between inflation and economic activity for the output gap. Wage and wage-bill data itself (macro_brasil.mt_pnad) is already documented from the wage-price-spiral angle in inflation_data_inventory.md §6 — this agent would own that table, with inflation as a consumer, mirroring the reciprocal relationship documented between economic activity and monetary policy. Scope boundary with the Qual - Economic Activity tab: business-cycle theory (RBC, DSGE), growth theory, and output-gap/potential-output measurement all stay there — this file's search/matching and NAIRU clusters are the labor-market-side companion to that file's output-gap cluster (5), not a substitute for it. The "hours worked" component of potential growth (bibliography cluster 9 there) is a Tier 2 dependency that file already lists as needed from this agent.
A69: Labor Market | B69: Literature | C69: (whole area) | D69: Suggested acquisition order | E69: 1. Ulyssea (2018) and Meghir, Narita & Robin (2015) — the two-paper core of this bibliography's most distinctive contribution; nothing else here is as directly load-bearing for explaining the Brazilian labor market's central structural feature (informality) to a reader. 2. Harris & Todaro (1970) — cheap, short, and the necessary theoretical setup before either 2015/2018 Brazil paper makes full sense. 3. Diamond (1982), Mortensen (1982), Pissarides (1985) — the three founding search-and-matching papers, read together since they're conventionally treated as a single package (and jointly earned their 2010 Nobel). 4. Borges (2022) — cheap (a blog post, not a paywalled journal article) and the single most current, load-bearing Brazil-specific number in the whole file (NAWRU ≈ 8.5%). 5. Everything else, roughly in cluster order — the Pissarides (2000) and Blanchflower-Oswald (1994) book chapters, and the two Brazilian official methodology notes (PNAD Contínua, CAGED), are lower urgency since their core content is already summarized secondhand elsewhere or is reference material rather than argument-bearing.
A70: Labor Market | B70: Literature | C70: #search_matching_theory_foundations | D70: the DMP framework: why unemployment and vacancies coexist
A71: Labor Market | B71: Literature | C71: #beveridge_curve_and_matching_efficiency | D71: the empirical signature of search frictions, and when it shifts
A72: Labor Market | B72: Literature | C72: #nairu_and_natural_rate_of_unemployment | D72: what "full employment" means, and how imprecisely it can be estimated | E72: Cross-reference, not re-acquired: Friedman, M. (1968), "The Role of Monetary Policy" — already acquired under monetary_policy/ and cross-referenced in the Qual - Inflation tab cluster 1 as the natural-rate hypothesis's founding statement. This cluster covers the estimation problem the natural rate concept creates, not its original theoretical statement.
A73: Labor Market | B73: Literature | C73: #unemployment_volatility_and_wage_rigidity | D73: why the basic DMP model doesn't move enough, and how to fix it
A74: Labor Market | B74: Literature | C74: #wage_curve_and_bargaining | D74: the empirical wage-unemployment relationship
A75: Labor Market | B75: Literature | C75: #minimum_wage_theory_and_evidence | D75: does it cost jobs, and under what conditions | E75: Brazil relevance note: the minimum wage (salário mínimo) plays an outsized role in Brazil relative to most economies, since it's also the indexing base for a large share of pension and social-benefit payments (Previdência, BPC) — its labor-market effects and its fiscal effects are unusually entangled here, which cluster 8 picks up on the institutional side.
A76: Labor Market | B76: Literature | C76: #informality_dual_labor_markets_and_development | D76: the segment of the Brazilian labor market international theory was built to explain
A77: Labor Market | B77: Literature | C77: #brazil_labor_market_institutions_and_measurement | D77: the CLT, the 2017 reform, and how the data itself is built
A78: Exchange Rate | B78: Data | C78: 1. Spot price | D78: resolved (2026-07) | E78: Why it matters: the dependent variable — every other category in this inventory exists to explain moves in this one series. Script: domain/db/brasil/bcb/cmb_ptax.py. Daily series — historical load chunks by year (BCB API rejects windows > 10 years for daily series, confirmed via 406 response). Remaining gap: the analysis agent (analytics/brasil/exchange_rate/agent_data.py) hasn't been updated yet to pull cmb_ptax into its snapshot — the data exists but isn't wired into the agent's output.
A79: Exchange Rate | B79: Data | C79: 2. Interest rate differential (carry) | E79: Why it matters: Selic and Fed Funds are the domestic and foreign legs of every carry argument (Verde's §3.1/§3.2 mental models). The real ex-post differential is the UIP-relevant comparison — it strips the pure inflation-differential effect out of the real-rate signal — while the ex-ante version is what markets are actually pricing, which is the input UIP and the fair-value models in the bibliography's cluster 2 actually need. The cupom cambial is the BCB's own named gauge for the cost of onshore dollar liquidity, Brazil's local instance of the CIP-basis concept, and Verde's tracked carry instrument (§3.4); DOL/WDO futures give the market-implied forward points directly. Script: domain/db/international/fred/diferenciais_juros.py. Full history load (2026-07): selic (SGS 432, daily) is chunked in 8-year windows to avoid the BCB API's 406 on windows > 10 years. Gaps:
A80: Exchange Rate | B80: Data | C80: 3. Terms of trade / commodity prices | E80: Why it matters: the aggregate index is the signal behind every commodity-exporter currency argument (BEER's fundamental driver set, GSFEER's current-account channel). Individual commodity prices decompose which commodity is driving a move — needed to tell a structural, volume-driven surplus from a cyclical, price-driven one (Verde's §2.1/§2.2). Script: domain/db/brasil/ipea/cmb_termos_troca.py. Source: Funcex, via the IPEADATA OData API (connectors/ipeadata.py) — not BCB SGS. Correction (2026-07): the previous entries here (termos_de_troca_a/b, BCB SGS 22099/22100) were confirmed to be National Accounts (GDP) series, not terms of trade — BCB SGS does not publish a terms-of-trade index at all. Those two series and their rows were removed from cmb_termos_troca. Gaps:
A81: Exchange Rate | B81: Data | C81: 4. Balance of payments | E81: Why it matters: the flow-side counterpart to the trade-balance/capital-account identity at the base of the whole determination cluster. The FDI-vs-portfolio split is not cosmetic: FDI is the safest instrument in the capital-inflow riskiness ranking (Ostry et al. 2010), portfolio flows the riskier and more reversible counterpart — and that split is what the capital-controls literature (bibliography cluster 7) is built around, so tracking them separately is what lets crisis vulnerability be read at all. Script: domain/db/brasil/bcb/cmb_balanco_pagmt.py. BPM6 methodology. Gaps: none identified at this time — coverage considered complete for the current FX report's purposes.
A82: Exchange Rate | B82: Data | C82: 5. FX flow (registered vs. contracted) | E82: Why it matters: registered flow is the broadest registered-channel measure, the empirical counterpart to the flow-supply/demand channel in the current-account-adjustment framework; contracted FX is the transactional, settlement-level view of the same market. Two distinct tables measuring different channels — not substitutes for one another:
A83: Exchange Rate | B83: Data | C83: 5a. Registered FX flow (BCB Nota Cambial) | E83: Script: domain/db/brasil/bcb/cmb_fluxo_cambial.py. Coverage: 2003 → today. Gaps: CEP/CBE sub-items of the financial flow (finer granularity, published in the weekly Nota Cambial) — candidate SGS codes (24372–24376) unconfirmed. Commercial balance (24366) timed out during research — can be derived as comercial_entrada − comercial_saida if needed.
A84: Exchange Rate | B84: Data | C84: 5b. Contracted FX (bank-client movement) | E84: Script: domain/db/brasil/bcb/cmb_cambio_contratado.py. ~46k observations. Conceptual difference: cmb_cambio_contratado measures bank-client settlements (BCB Tables 13/14); cmb_fluxo_cambial (24xxx codes) is a broader measure covering all registered channels — the two should not be summed or treated as equivalent.
A85: Exchange Rate | B85: Data | C85: 6. International reserves and BCB intervention | E85: Why it matters: the stock side is how much ammunition the BCB has, central to every fixed/managed-rate defense argument in the bibliography's cluster 3. Banks' net FX spot position is the banking-system mirror of the carry trade (posicao_vendida_carry_incentive in the conceptual map, sourced from the BCB's own technical note) — who is actually short or long FX onshore. The swap position is the off-balance-sheet instrument the BCB uses instead of spot intervention, and the repo-line stock is temporary liquidity, distinct from a permanent reserves change. The intervention series are the flow side: what the BCB is doing right now, as opposed to what it holds. Script: domain/db/brasil/bcb/cmb_reservas_bc.py. ~19k observations total. Full detail in analytics/brasil/exchange_rate/CLAUDE.md. Coverage considered robust — includes both the stock (reserves, bank position, swap) and the intervention flow (BCB's net buying/selling in spot and forwards), which lets the agent distinguish "how much the BCB has" from "what the BCB is doing right now." Gaps: none identified — the historical "gross reserves" pending item (SGS 13127, timeout) has been superseded by using the liquidity concept plus detailed components.
A86: Exchange Rate | B86: Data | C86: 7. Real effective exchange rate (REER) | E86: Why it matters: the core equilibrium-valuation benchmark underlying BEER/GSDEER-style arguments. The peer set is what lets BRL's REER move be read relative to comparable currencies rather than in isolation — which matters more here than it would elsewhere, since the base's non-Brazil EM depth is otherwise thin (see bibliography cluster 3). Script: domain/db/international/bis/cmb_reer.py. Source: BIS Statistics API. Gaps:
A87: Exchange Rate | B87: Data | C87: 8. Speculative positioning (FX futures) | E87: Why it matters: the standard futures-market positioning gauge, and the data behind Verde's §5.3 positioning-as-contrarian-signal mental model. Options-based positioning (skew, risk reversal) would be the volatility-market complement — it ties directly to the FX-options gap in bibliography cluster 1 (Garman-Kohlhagen and the options/risk-reversal primer), so the data gap and the literature gap here are the same gap seen from two sides. Script: domain/db/international/cftc/cmb_cot_fx.py. Source: CFTC Traders in Financial Futures. Gaps:
A88: Exchange Rate | B88: Data | C88: 9. Inflation differential and market expectations | E88: Why it matters: IPCA and US CPI are the two legs needed to turn the nominal Selic–Fed Funds spread into a real one (§2). Focus is the forward-looking domestic input the ex-ante differential needs, and the raw material for any credibility/anchoring argument (Verde's §1.7). Scripts: domain/db/brasil/bcb/inflc_agregados.py, domain/db/brasil/bcb/expc_focus.py. Use for FX analysis: expc_focus is already ready to feed the pending ex-ante differentials (item 2 above) — Focus Selic EOP 12m and Focus IPCA 12m are already available; only the script combining them with the US side is missing.
A89: Exchange Rate | B89: Data | C89: 10. Domestic activity backdrop (context, not FX-specific) | E89: Not an FX category, kept as context. The presentation-layer copy merged in here dropped this section outright, on the grounds that it is general macro backdrop rather than FX-specific data — a fair call for a reading audience, but the series are worth keeping listed for the agent. General macro_brasil series that help contextualize the domestic cycle (relevant for carry/country risk, but not "FX data" per se): atv_ibcbr (monthly GDP proxy), atv_pib, atv_pim (industrial production), atv_pmc/atv_pms (retail/services), mt_pnad (labor market), mt_caged, cred_credito_amplo, cred_credito_familias. Full table in CLAUDE.md. On the US side, activity/inflation data today only exists ad hoc inside analytics/oraculo/us/term_us.py (via FRED) — there's no persistent macro_us schema equivalent to macro_brasil (already logged as a pending item in CLAUDE.md, "Média prioridade — US expandir dados").
A90: Monetary Policy | B90: Data | C90: 1. Policy rate & COPOM decision history | D90: GAP | E90: There is no dedicated table recording COPOM decisions as discrete events (meeting date, rate before/after, change in bps, vote count/dissent). The Selic level only exists today embedded inside macro_international.diferenciais_juros (series selic, sourced from BCB SGS 432) as a continuous monthly series for computing rate differentials — it was never built to answer "what did COPOM actually decide, and how divided was the committee, at each meeting." Impact: without this, the agent can't backtest a reaction function against actual historical decisions, or characterize dissent/unanimity patterns (directly relevant to reading credibility, per the Barro-Gordon/Rogoff literature already in the bibliography). Possible approach: a copom_decisions table — (meeting_date, selic_before, selic_after, change_bps, votes_for, votes_against, unanimous) — sourced from BCB SGS 432 (which already carries COPOM meeting dates, not calendar dates) plus vote counts parsed from the Ata once §8 of the bibliography is acquired. No script built yet.
A91: Monetary Policy | B91: Data | C91: 2. Interest rate differentials (carry) | E91: Script: domain/db/international/fred/diferenciais_juros.py. Same table already documented from the FX angle in exchange_rate_data_inventory.md §2 — for monetary policy the read is different: this is the agent's primary evidence of where policy stance sits relative to global conditions, not just a carry-trade input. Gaps (same underlying ones as the FX inventory, restated for this agent's purposes):
A92: Monetary Policy | B92: Data | C92: 3. Market-implied rate expectations | E92: Script: domain/db/brasil/bcb/expc_focus.py. This is genuinely useful, already-available data — the agent can compare its own reaction-function output against what professional forecasters expect BCB to do, without waiting on any other agent. Gaps:
A93: Monetary Policy | B93: Data | C93: 4. Real interest rate & neutral rate (r*) | D93: largely a GAP | E93: Gaps:
A94: Monetary Policy | B94: Data | C94: 5. COPOM primary-source communications | E94: Covered in monetary_policy_bibliography_candidates.md §8 (Comunicado, Ata, Relatório de Política Monetária). Not data in the numeric-series sense — text. Retention window and ingestion mechanism explicitly deferred in that file; not repeated here. Once acquired, the RPM in particular would also be the natural source for BCB's own r* assumption (see item 4).
A95: Monetary Policy | B95: Data | C95: 6. Inflation target regime parameters | D95: GAP, low effort to close | E95: No table records the history of the target itself: the numeric target, tolerance band width, and target horizon, as set by CMN (Conselho Monetário Nacional) resolutions, which have changed several times since 1999 (target level, band width, and the horizon convention have all been revised over the years). This is small, slow-moving, easy to build (a short lookup table by year) but currently doesn't exist anywhere — without it, the agent can't correctly compute an inflation gap even once it has an inflation forecast, since "the target" isn't a fixed constant across the whole sample.
A96: Monetary Policy | B96: Data | C96: 7. Global monetary conditions | E96: Gaps: only the Fed is covered. No broader global policy-rate context (ECB, other EM central banks) for situating BCB within the "global financial cycle" framing central to the Rey (2013) / Obstfeld (2015) debate in the bibliography's #global_spillovers_em_autonomy cluster. Low priority unless a specific cross-country comparison becomes necessary.
A97: Monetary Policy | B97: Data | C97: Tier 2 | E97: None of this exists yet in any form — these are the structured outputs the monetary policy agent will need to request once each supplying agent is actually scoped and built. Listed here so the dependency is visible now rather than discovered later.
A98: Monetary Policy | B98: Data | C98: Tier 2 — From the exchange rate agent (already substantially built | D98: see exchange_rate_data_inventory.md) | E98: This dependency is less hypothetical than the three above, since the underlying FX data pipeline already exists (cmb_reservas_bc, cmb_fluxo_cambial, cmb_reer, cmb_cot_fx, cmb_balanco_pagmt). What's still missing is the packaging into a monetary-policy-ready number:
A99: Monetary Policy | B99: Data | C99: Tier 2 — How to update this inventory | E99: Tier 1: when a new owned table/series is built (e.g. copom_decisions, an r* estimate), update the relevant section and remove/adjust the corresponding gap-summary row. Tier 2: when a new specialist agent (inflation, activity, fiscal, or a global/markets agent) gets scoped, replace its placeholder bullet list with the actual table/column references that agent produces, the same way Tier 1 entries are documented — and note the hand-off format (e.g. a shared table, an API call, a structured file) once that's decided.
A100: Economic Activity | B100: Data | C100: 1. Quarterly GDP (Contas Nacionais Trimestrais) | E100: Script: domain/db/brasil/ibge/atv_pib.py. IBGE aggregados 1620 (NSA)/1621 (SA), volume-index series. This is a genuinely complete both-sides-of-GDP dataset — supply and demand decomposition together, which many countries' own statistical agencies don't publish this readily disaggregated. Gaps:
...

Sheet Qual - Exchange Rate
A1: Name | B1: Autor/Company | C1: Date | D1: Importance (1-5) | E1: Do we have it? | F1: Type | G1: Cluster | H1: Why | I1: Comments | J1: File | K1: Ingestion | L1: Ingested on | M1: Extraction | N1: QC flags | O1: Synthesis | P1: Ingestion note
A2: Foreign Currency Option Values | B2: Garman, M. & Kohlhagen, S. | C2: 1983 | D2: 5 | E2: No | F2: Paper | G2: #market_microstructure | H2: The FX-adapted Black-Scholes model — the canonical closed-form FX option pricing formula. Fills the one theoretical area (options/volatility) with zero representation in the base, despite forwards, swaps and futures all being covered elsewhere.
A3: The Foreign Exchange Market (CFA L1) | B3: Barker, McNelis & Nickelsburg / CFA Institute | C3: 2025 | D3: 3 | E3: Yes | F3: CFA curriculum reading | G3: #market_microstructure | H3: Standard practitioner map of FX market plumbing: buy-side vs. sell-side structure, the swap/spot/forward turnover split (BIS Triennial Survey), quoting hierarchy, and the impossible trinity — the baseline reference underlying every other source's implicit assumptions about liquidity and quoting conventions. | J3: capital_flow_fx_market (CFA L1, 2025) | K3: Ingested | L3: 2026-10-20 | M3: reclean (cleaner change) | O3: Yes
A4: Exchange Rate Calculations (CFA L1) | B4: CFA Institute | C4: 2025 | D4: 3 | E4: Yes | F4: CFA curriculum reading | G4: #market_microstructure | H4: The calculation toolkit — cross-rate/triangular-arbitrage mechanics, forward points, and covered interest rate parity (CIP) as a no-arbitrage identity — that the entire parity-conditions cluster (UIP, real interest parity) is built on top of. | J4: exchange_rate_calculation (CFA L1, 2025) | K4: Ingested | L4: 2026-10-20 | M4: reclean (cleaner change) | O4: Yes
A5: Posicao de Cambio, Saldo Cambial, Disponibilidade Cambial e Exposicao Cambial | B5: Banco Central do Brasil | C5: 2020 | D5: 4 | E5: Yes | F5: Central bank technical note | G5: #market_microstructure | H5: The BCB's own precise disambiguation of four related-but-distinct FX plumbing concepts (position, flow, availability, exposure) plus its concrete intervention toolkit (spot auctions vs. repo-style line auctions vs. FX swaps), illustrated with a real 2019 case cushioning a projected US$70bn short position down to US$34bn. Essential ground truth for reading any BCB-published FX market data. | J5: posicao_de_cambio (BCB, 2020) | K5: Ingested | L5: 2026-10-20 | M5: reclean (cleaner change)
A6: Currency options / risk reversals primer (source TBD) | B6: CFA curriculum or bank research | C6: TBD | D6: 2 | E6: No | F6: Paper / practitioner note | G6: #market_microstructure | H6: Placeholder for a positioning-and-skew-as-signal companion to Garman-Kohlhagen's pricing model, ideally at the same practitioner register as the existing CFA/Goldman sources — would close the "options as an FX sentiment/positioning indicator" half of the gap.
A7: Expectations and Exchange Rate Dynamics | B7: Dornbusch, R. | C7: 1976 | D7: 5 | E7: Yes | F7: Paper | G7: #exchange_rate_determination | H7: The founding overshooting model — sticky goods prices plus instantaneously-clearing asset markets mean a permanent monetary shock makes the exchange rate depreciate more than its long-run equilibrium level before appreciating back as prices catch up. The single most-cited explanation for why FX volatility so badly outpaces relative-price-level volatility. | J7: expectations_and_exchange_rate_dynamics (Dornbusch, 1976) | K7: Ingested | L7: 2026-10-20 | M7: reclean (cleaner change) | O7: Yes
A8: Forward and Spot Exchange Rates | B8: Fama, E. | C8: 1984 | D8: 5 | E8: Yes | F8: Paper | G8: #exchange_rate_determination | H8: The original "wrong-signed beta" UIP-failure econometrics — the single most-cited empirical fact behind the forward-premium/carry-trade puzzle. Shows most of the variance in the forward-spot differential is risk-premium variance, not genuine forecast information, and catalogs the competing explanations (irrationality, official "leaning against the wind," the peso problem, Fama-Gibbons/Mundell-Tobin real-rate effects) the field still adjudicates between four decades later. | J8: forward_spot_exchange (Fama, 1984) | K8: Ingested | L8: 2026-10-20 | M8: reclean (cleaner change)
A9: Anomalies: Foreign Exchange | B9: Froot, K. & Thaler, R. | C9: 1990 | D9: 4 | E9: Yes | F9: Paper (survey) | G9: #exchange_rate_determination | H9: Accessible, non-technical survey of the forward premium puzzle — good complement if you want context/synthesis alongside the raw econometrics | I9: Acquisition priority: Low (survey, optional) Suggested file: fx_anomalies_survey (Froot & Thaler, 1990).pdf | J9: fx_anomalies_survey (Froot & Thaler, 1990) | K9: Ingested | L9: 2026-10-20 | M9: reclean (cleaner change)
A10: International Economics, Ch. 14 - Exchange Rates and the Foreign Exchange Market | B10: Krugman, Obstfeld & Melitz | C10: 2023 | D10: 4 | E10: Yes | F10: Textbook chapter | G10: #exchange_rate_determination | H10: The standard textbook formalization of UIP as the FX market's core equilibrium condition, and the asset-approach reframing of exchange rates as forward-looking asset prices rather than goods prices — the spine the whole determination cluster organizes around. | J10: exchange_rate_foreign_exchange_market (Krugman, 2023) | K10: Ingested | L10: 2026-10-20 | M10: reclean (cleaner change) | O10: Yes
A11: International Economics, Ch. 15 - Money, Interest Rates, and Exchange Rates | B11: Krugman, Obstfeld & Melitz | C11: 2023 | D11: 4 | E11: Yes | F11: Textbook chapter | G11: #exchange_rate_determination | H11: Textbook derivation of Dornbusch overshooting via the money-market/interest-parity diagram, the long-run-monetary-neutrality "currency reform" intuition, and Latin American money-growth/inflation scatter evidence (1980–2014) grounding the quantity-theory logic empirically. | J11: money_interest_rate_exchange_rates (Krugman, 2023) | K11: Ingested | L11: 2026-10-20 | M11: reclean (cleaner change) | O11: Yes
A12: International Economics, Ch. 16 - Price Levels and the Exchange Rate in the Long Run | B12: Krugman, Obstfeld & Melitz | C12: 2023 | D12: 4 | E12: Yes | F12: Textbook chapter | G12: #exchange_rate_determination | H12: Long-run PPP/monetary-approach chapter — derives real interest rate parity as an accounting identity (not an empirical requirement), formalizes the Balassa-Samuelson effect behind BEER-style models, and reports Frankel & Rose's ~4-year PPP-deviation half-life, independently corroborating GSDEER's convergence-speed estimate. | J12: price_levels_exchange_rate_lr (Krugman, 2023) | K12: Ingested | L12: 2026-10-20 | M12: reclean (cleaner change) | O12: Yes
A13: Currency Exchange Rates: Understanding Equilibrium Value (CFA L2) | B13: CFA Institute | C13: 2025 | D13: 4 | E13: Yes | F13: CFA curriculum reading | G13: #exchange_rate_determination | H13: The densest single synthesizing source in the base (78pp) — ties UIP, CIP, ex ante PPP, real interest parity and the international Fisher effect into one master parity-conditions diagram, and is the direct source of the carry-trade return-distribution mechanics (fat tails, negative skew) used throughout the base. | J13: exchange_rate_understanding_equilibrium (CFA L2, 2025) | K13: Ingested | L13: 2026-10-20 | M13: reclean (cleaner change) | O13: Yes
A14: A Theory of Optimum Currency Areas | B14: Mundell, R.A. | C14: 1961 | D14: 5 | E14: Yes | F14: Paper | G14: #currency_regimes | H14: The founding OCA paper — defines the optimal domain for a shared currency as the region with high internal and low external factor mobility, not any particular political border. Directly prefigures the euro debate three decades early via the Meade-Scitovsky exchange cited in the paper. | J14: theory_optimum_currency_areas (Mundell, 1961) | K14: Ingested | L14: 2026-10-20 | M14: reclean (cleaner change)
A15: Capital Mobility and Stabilization Policy Under Fixed and Flexible Exchange Rates | B15: Mundell, R.A. | C15: 1963 | D15: 5 | E15: Yes | F15: Paper | G15: #currency_regimes | H15: The founding Mundell-Fleming result — under perfect capital mobility, monetary policy is powerful under floating rates and impotent under fixed rates, and fiscal policy is the mirror image. The paper the impossible trinity and every fixed-vs-floating policy-effectiveness argument in the base ultimately traces back to. | J15: capital_mobility_exchange_rates_regimes (Mundell, 1963) | K15: Ingested | L15: 2026-10-20 | M15: reclean (cleaner change) | O15: Yes
A16: Optimum Currency Areas | B16: McKinnon, R. | C16: 1963 | D16: 5 | E16: No | F16: Paper | G16: #currency_regimes | H16: The second classic OCA criterion (economic openness) — the standard complement to Mundell (1961); together with Kenen (1969), completes the canonical Mundell/McKinnon/Kenen OCA trio still taught as the field's baseline.
A17: The Theory of Optimum Currency Areas: An Eclectic View | B17: Kenen, P. | C17: 1969 | D17: 5 | E17: No | F17: Paper | G17: #currency_regimes | H17: The third classic OCA criterion (production diversification as a buffer against asymmetric shocks) — closes the canonical OCA trio alongside Mundell (1961) and McKinnon (1963).
A18: Exchange Rates and Financial Fragility (NBER WP 7418) | B18: Eichengreen, B. & Hausmann, R. | C18: 1999 | D18: 5 | E18: Yes | F18: Paper | G18: #currency_regimes | H18: The paper that coined "original sin" — EM inability to borrow abroad in local currency, and how that shapes exchange-rate-regime choice | I18: Acquisition priority: High Suggested file: original_sin_em_debt (Eichengreen & Hausmann, 1999).pdf Also feeds #currency_crisis_dynamics | J18: original_sin_em_debt (Eichengreen & Hausmann, 1999) | K18: Ingested | L18: 2026-10-20 | M18: reclean (cleaner change)
A19: International Economics, Ch. 18 - Fixed Exchange Rates and Foreign Exchange Intervention | B19: Krugman, Obstfeld & Melitz | C19: 2023 | D19: 4 | E19: Yes | F19: Textbook chapter | G19: #currency_regimes | H19: The textbook mechanics of defending a peg — central bank balance-sheet mechanics, sterilized vs. non-sterilized intervention, the risk-premium channel under imperfect asset substitutability, and the reserve-currency asymmetry that let the US never have to intervene under Bretton Woods. | J19: fixed_exchange_rate_intervention (Krugman, 2023) | K19: Ingested | L19: 2026-10-20 | M19: reclean (cleaner change) | O19: Yes
A20: Renminbi Internationalization: Achievements, Prospects, and Challenges | B20: Eichengreen, B. & Kawai, M. | C20: 2014 | D20: 3 | E20: Yes | F20: Paper | G20: #currency_regimes | H20: Gives a concrete non-Brazil EM case study — RMB internationalization and managed-float mechanics, a natural parallel to the BCB posicao_de_cambio piece already in the base | I20: Acquisition priority: Medium Suggested file: rmb_internationalization (Eichengreen & Kawai, 2014).pdf Also feeds #market_microstructure | J20: rmb_internationalization (Eichengreen & Kawai, 2014) | K20: Ingested | L20: 2026-10-20 | M20: reclean (cleaner change)
A21: International Economics, Ch. 13 - National Income Accounting and the Balance of Payments | B21: Krugman, Obstfeld & Melitz | C21: 2023 | D21: 4 | E21: Yes | F21: Textbook chapter | G21: #balance_of_payments | H21: The accounting-identity backbone of the whole balance-of-payments cluster — X−M = (S−I)+(T−G), the twin-deficits decomposition, and the BPM6 current/capital/financial account structure that later sources (Paiva's BEER, the GSFEER current-account-gap model) build directly on top of. | J21: national_income_balance_payments (Krugman, 2023) | K21: Ingested | L21: 2026-10-20 | M21: reclean (cleaner change)
A22: Invested Interests: The Politics of National Economic Policies in a World of Global Finance | B22: Frieden, J. | C22: 1991 | D22: 5 | E22: Yes | F22: Paper | G22: #policy_transmission | H22: The canonical political-economy-of-exchange-rates paper — maps which domestic sectors (import-competing tradables, export tradables, nontradables, international investors) favor currency stability vs. policy autonomy, and a weak vs. strong currency. Gives a formal "who wins, who loses" mechanism behind any specific country's currency-regime politics, including Brazil's own. | J22: invested_interest (Frieden, 1991) | K22: Ingested | L22: 2026-10-20 | M22: reclean (cleaner change)
A23: International Economics, Ch. 17 - Output and the Exchange Rate in the Short Run | B23: Krugman, Obstfeld & Melitz | C23: 2023 | D23: 4 | E23: Yes | F23: Textbook chapter | G23: #policy_transmission | H23: The DD-AA model plus the Marshall-Lerner condition and the J-curve — the formal elasticity conditions under which a depreciation actually improves (rather than worsens) the trade balance, and the mechanism by which a weak short-run J-curve response amplifies Dornbusch overshooting. | J23: output_exchange_rates_sr (Krugman, 2023) | K23: Ingested | L23: 2026-10-20 | M23: reclean (cleaner change) | O23: Yes
A24: The Political Economy of International Monetary Relations | B24: Broz, J.L. & Frieden, J. | C24: 2001 | D24: 3 | E24: Yes | F24: Paper (survey) | G24: #policy_transmission | H24: A single-source field survey of exchange-rate political economy — useful as a broader, updated overview alongside Frieden's original 1991 sectoral-interests paper. | J24: political_economy_international_monetary_relations (Broz & Frieden, 2001) | K24: Ingested | L24: 2026-10-20 | M24: reclean (cleaner change)
A25: External Adjustment and Equilibrium Exchange Rate in Brazil (IMF WP/06/221) | B25: Paiva, C. | C25: 2006 | D25: 4 | E25: Yes | F25: Paper | G25: #applied_valuation_tools | H25: Applies the BEER (Behavioral Equilibrium Exchange Rate) methodology to Brazil via Johansen cointegration — finds the real's 2003–05 appreciation was largely an equilibrium phenomenon (net foreign asset position + terms of trade), a direct empirical counterpoint to reading any large REER move as automatic misalignment. | J25: equilibrium_exchange_brazil (Paiva, 2006) | K25: Ingested | L25: 2026-10-20 | M25: reclean (cleaner change) | O25: Yes
A26: GSDEER - A User's Guide | B26: Bhushan & Cahill, Goldman Sachs | C26: 2023 | D26: 3 | E26: Yes | F26: Practitioner research note | G26: #applied_valuation_tools | H26: Goldman's own methodology note for its Dynamic Equilibrium Exchange Rate model (PPP adjusted for terms of trade and productivity) — documents which component actually drives fair value by currency (inflation for EUR/GBP/CAD, terms of trade for commodity exporters) and the empirical convergence timeline (~3 years to beat a random walk, ~5 years to fully converge, ~20%/year closure rate). | J26: gsdeer_manual_guide (Goldman, 2023) | K26: Ingested | L26: 2026-10-20 | M26: reclean (cleaner change) | O26: Yes
A27: Primer: GSDEER and GSFEER | B27: Alves & Jenkins, Goldman Sachs | C27: 2025 | D27: 3 | E27: Yes | F27: Practitioner research note | G27: #applied_valuation_tools | H27: Introduces GSFEER (the macro-balance-approach cousin to GSDEER, based on the current-account gap vs. its savings/investment "norm") and Goldman's own model-blending weights by horizon. Flags that GSDEER and GSFEER currently give directionally different fair-value signals for BRL specifically, concluding carry and terms-of-trade dominate BRL price action over either anchor. | J27: primer_gsdeer_gsfeer (Goldman, 2025) | K27: Ingested | L27: 2026-10-20 | M27: reclean (cleaner change) | O27: Yes
A28: Capital Inflows: The Role of Controls (IMF SPN/10/04) | B28: Ostry, Ghosh, Habermeier, Chamon, Qureshi & Reinhardt | C28: 2010 | D28: 4 | E28: Yes | F28: Paper | G28: #capital_controls | H28: The empirical/pragmatic precursor to the IMF's later institutional view — lays out a policy decision sequence (let the currency appreciate → accumulate reserves → sterilize → adjust monetary/fiscal policy → controls as last resort) and a four-condition test for when inflow controls are justified. Finds controls have little robust effect on aggregate inflow volume or appreciation, but real, demonstrable effects on the maturity composition of external liabilities. | J28: capital_inflow (IMF, 2010) | K28: Ingested | L28: 2026-10-20 | M28: reclean (cleaner change)
A29: The Liberalization and Management of Capital Flows: An Institutional View | B29: IMF Staff (Arora, Habermeier, Ostry, Weeks-Brown et al.) | C29: 2012 | D29: 5 | E29: Yes | F29: Official institutional doctrine | G29: #capital_controls | H29: The IMF's own standing official doctrine on capital account liberalization and management — introduces the CFM/MPM terminology distinction, a liberalization sequencing framework ("long before short, FDI before debt, inflows before outflows"), and explicit design criteria (transparent, targeted, temporary, non-discriminatory) for when new controls are appropriate. The single most citable "what does official policy actually say" reference in this cluster. | J29: the_liberalization_management_capital_flows (IMF, 2012) | K29: Ingested | L29: 2026-10-20 | M29: reclean (cleaner change)
A30: Capital Controls in Brazil: Effective? | B30: Chamon, M. & Garcia, M. | C30: 2016 | D30: 4 | E30: Yes | F30: Paper | G30: #capital_controls | H30: Direct empirical test of Brazil's own 2008–2012 IOF-tax episode — the natural Brazil-specific complement the general capital-controls framework above is missing, and the base's most direct empirical evidence on whether Brazil's own use of the tool actually worked. | J30: capital_controls_brazil (Chamon & Garcia, 2016) | K30: Ingested | L30: 2026-10-20 | M30: reclean (cleaner change)
A31: Modelos Mentais de Cambio - Verde Asset Management (2020-2026) | B31: Verde Asset Management (internal synthesis) | C31: 2020-2026 | E31: Yes | F31: Practitioner mental model | G31: #practitioner_mental_models | H31: Consolidated from 73 monthly letters (Jan/2020–May/2026), 507 identified mental-model instances, organized into 5 clusters (Brazil fiscal/credit/institutions; external fundamentals/commodities; carry & rate differentials; global dollar cycle & the Fed; flows/positioning/risk appetite), each with dated, quoted real-world applications. | I31: Mental-model synthesis status: Done
A32: Kinea Insights - mental-model synthesis | B32: Kinea Investimentos (internal synthesis, pending) | C32: 2021-2026 | E32: Yes | F32: Practitioner mental model | G32: #practitioner_mental_models | H32: 60 "Carta do Gestor" letters (repository/mental_model/kinea/) plus the 64 Kinea Insights notes (repository/mental_model/kinea_insights/). | I32: Mental-model synthesis status: Done
A33: Modelos Mentais de Câmbio — Kapitalo | B33: Kapitalo | E33: Yes | F33: Practitioner mental model | G33: #practitioner_mental_models | H33: 83 K10 letters, Jul/2019–Mai/2026 (repository/mental_model/kapitalo/). | I33: Mental-model synthesis status: Done
A34: Goldman Sachs Global FX Trader | B34: Goldman Sachs Global FX Trader | E34: Partial | F34: Practitioner mental model | G34: #practitioner_mental_models | H34: First 25 of ~80 weekly issues processed (repository/mental_model/goldman_sachs/). | I34: Mental-model synthesis status: Partial
A35: SPX Capital | B35: SPX Capital | E35: No | F35: Practitioner mental model | G35: #practitioner_mental_models | H35: 7 PDFs in repository/mental_model/spx_capital/, not reviewed. | I35: Mental-model synthesis status: Not built
A36: A Model of Balance-of-Payments Crises | B36: Krugman, P. | C36: 1979 | D36: 5 | E36: Yes | F36: Paper | G36: #currency_crisis_dynamics | H36: The founding first-generation crisis model - rational speculators attack before reserves would have run out anyway. | J36: balance_of_payment_crisis (Krugman, 1979) | K36: Ingested | L36: 2026-10-20 | M36: reclean (cleaner change)
A37: Collapsing Exchange-Rate Regimes: Some Linear Examples | B37: Flood, R.P. & Garber, P.M. | C37: 1983 | D37: 4 | E37: Yes | F37: Paper | G37: #currency_crisis_dynamics | H37: Standard linear, closed-form companion to Krugman (1979) - introduces the 'shadow exchange rate' technique for solving collapse timing. | J37: collapsing_exchange_rate_regimes (Flood, 1983) | K37: Ingested | L37: 2026-10-20 | M37: reclean (cleaner change)
A38: Balance-of-Payments Crises and Devaluation (NBER WP 1486) | B38: Obstfeld, M. | C38: 1984 | D38: 5 | E38: Yes | F38: Paper | G38: #currency_crisis_dynamics | H38: The original second-generation, self-fulfilling crisis model - working-paper precursor to Obstfeld's canonical 1986 AER piece. | J38: rational_self_fulfilling_bpc (Obstfeld, 1984) | K38: Ingested | L38: 2026-10-20 | M38: reclean (cleaner change)
A39: The Logic of Currency Crises (NBER WP 4640) | B39: Obstfeld, M. | C39: 1994 | D39: 3 | E39: Yes | F39: Paper (survey) | G39: #currency_crisis_dynamics | H39: Accessible single-source synthesis bridging first- and second-generation crisis logic. | J39: logic_currency_crises (Obstfeld, 1994) | K39: Ingested | L39: 2026-10-20 | M39: reclean (cleaner change)
A40: Financial Crises in Emerging Markets: A Canonical Model | B40: Chang, R. & Velasco, A. | C40: 1998 | D40: 5 | E40: Yes | F40: Paper | G40: #currency_crisis_dynamics | H40: One of two competing third-generation models of the 1997-98 Asian crisis - open-economy Diamond-Dybvig bank-run model. | J40: financial_crises_emerging_markets (Chang, 1998) | K40: Ingested | L40: 2026-10-20 | M40: reclean (cleaner change)
A41: Balance Sheets, the Transfer Problem, and Financial Crises | B41: Krugman, P. | C41: 2000 | D41: 5 | E41: Yes | F41: Paper | G41: #currency_crisis_dynamics | H41: The other competing third-generation model - private-sector balance-sheet/currency-mismatch feedback loop; Krugman's own public reversal on self-fulfilling crises. | J41: bs_transfer_problem_financial_crises (Krugman, 2000) | K41: Ingested | L41: 2026-10-20 | M41: reclean (cleaner change)
A42: Capital Flows, Capital Controls and Currency Crisis: The Case of Brazil in the Nineties | B42: Garcia, M. & Valpassos, M. | C42: 1998 | D42: 3 | E42: Yes | F42: Paper | G42: #currency_crisis_dynamics | H42: Ties crisis theory directly to Brazil's own 1999 Real devaluation - the Brazil-specific case-study complement this cluster's otherwise non-Brazil model set is missing. | J42: capital_flows_controls_brazil_nineties (Garcia & Valpassos, 1998) | K42: Ingested | L42: 2026-10-20 | M42: reclean (cleaner change)
A43: Exchange Rate Pass-Through in Brazil (IMF WP 03/141) | B43: Belaisch, A. | C43: 2003 | D43: 4 | E43: Yes | F43: Paper | G43: #policy_transmission | H43: VAR estimates of Brazil's pass-through after the 2001-02 depreciation: lower than earlier estimates and than in other Latin American countries, closer to the G-7, but faster | I43: IMF Working Paper 03/141 (July 2003) | J43: depreciation_pass_through (Belaisch, 2003) | K43: Ingested | L43: 2026-10-20 | M43: reclean (cleaner change) | O43: Yes
A44: The Pass-Through from Depreciation to Inflation: A Panel Study (PUC-Rio TD 423) | B44: Goldfajn, I. & Werlang, S. | C44: 2000 | D44: 4 | E44: Yes | F44: Paper | G44: #policy_transmission | H44: Cross-country panel of pass-through from depreciation to inflation and its determinants (output cycle, initial real-exchange-rate overvaluation, initial inflation, openness); the standard reference for why pass-through varies | I44: PUC-Rio Texto para Discussão 423 (2000) | J44: depreciation_pass_through (Goldfajn, 2000) | K44: Ingested | L44: 2026-10-20 | M44: reclean (cleaner change) | O44: Yes
A45: Padrões da transmissão cambial para taxa de inflação no Brasil (Nova Economia 33(2)) | B45: Araújo, E., Caldarelli, C. & Cortapasso, J. | C45: 2023 | D45: 3 | E45: Yes | F45: Paper | G45: #policy_transmission | H45: Brazil VAR 2002-2021: pass-through differs between appreciation and depreciation phases; the exchange rate used as a de facto price-control instrument under inflation targeting | I45: In Portuguese | J45: padrao_transmissao_cambial (Cortapasso, 2023) | K45: Ingested | L45: 2026-10-20 | M45: reclean (cleaner change) | O45: Yes

Sheet Quant - Exchange Rate
A1: Name | B1: Source | C1: Date | D1: Importance | E1: Do we have it? | F1: Category | G1: Comments
A2: PTAX sell (spot) | B2: macro_brasil.cmb_ptax · ptax_venda (SGS 1) | C2: 1994-07-01 → today, daily (Real Plan implementation — pre-Real data in extinct currencies excluded) | E2: Yes | F2: 1. Spot price
A3: Interbank FX volume, T+1/T+2 settlement | B3: macro_brasil.cmb_ptax · fx_interbank_vol_t1 (SGS 20359), fx_interbank_vol_t2 (SGS 20205) | C3: 1994-07-04 → today, daily | E3: Yes | F3: 1. Spot price
A4: Selic (raw) | B4: macro_international.diferenciais_juros · selic | C4: 1999-03 → today (SGS 432 has no earlier data) | E4: Yes | F4: 2. Interest rate differential (carry)
A5: Fed Funds (raw) | B5: macro_international.diferenciais_juros · fed_funds | C5: 1995 → today | E5: Yes | F5: 2. Interest rate differential (carry)
A6: Nominal ex-post differential | B6: macro_international.diferenciais_juros · diferencial_nominal | C6: 1999-03 → today | E6: Yes | F6: 2. Interest rate differential (carry)
A7: Real ex-post differential (Selic − IPCA vs. Fed Funds − CPI) | B7: macro_international.diferenciais_juros · real_br_ex_post, real_us_ex_post, diferencial_real | C7: 1999-03 → today | E7: Yes | F7: 2. Interest rate differential (carry)
A8: Terms of trade index (PX/PM, base 2018=100) | B8: macro_brasil.cmb_termos_troca · termos_de_troca_funcex (IPEADATA FUNCEX12_TTR12) | E8: Yes | F8: 3. Terms of trade / commodity prices | G8: 1978 → today, monthly
A9: Current account, trade balance+services, goods exports | B9: macro_brasil.cmb_balanco_pagmt · conta_corrente, balanca_comercial_servicos, exportacao_bens | C9: 2001 → today | E9: Yes | F9: 4. Balance of payments
A10: Financial account, FDI (net and inflows), outward FDI | B10: macro_brasil.cmb_balanco_pagmt · conta_financeira, investimento_direto_liquido, idp_ingressos, ide_saidas | C10: 2001 → today | E10: Yes | F10: 4. Balance of payments
A11: Portfolio investment (total, equities, fixed income) | B11: macro_brasil.cmb_balanco_pagmt · investimento_carteira, carteira_acoes, carteira_renda_fixa | C11: 2001 → today | E11: Yes | F11: 4. Balance of payments
A12: Total balance/inflow/outflow | B12: macro_brasil.cmb_fluxo_cambial · total_saldo, total_entrada, total_saida | E12: Yes | F12: 5a. Registered FX flow (BCB Nota Cambial)
A13: Commercial sector (inflow/outflow) | B13: macro_brasil.cmb_fluxo_cambial · comercial_entrada, comercial_saida | E13: Yes | F13: 5a. Registered FX flow (BCB Nota Cambial)
A14: Financial sector (balance) | B14: macro_brasil.cmb_fluxo_cambial · financeiro_saldo | E14: Yes | F14: 5a. Registered FX flow (BCB Nota Cambial)
A15: Daily — total balance, exports (total/ACC/PA/other), imports, commercial balance, financial purchases/sales/balance | B15: macro_brasil.cmb_cambio_contratado · cc_saldo_total, cc_export_*, cc_import_total, cc_saldo_comercial, cc_fin_compras, cc_fin_vendas, cc_fin_saldo | E15: Yes | F15: 5b. Contracted FX (bank-client movement)
A16: Monthly — detailed financial breakdown (services, income, domestic/foreign capital) | B16: macro_brasil.cmb_cambio_contratado · cc_fin_saldo_det, cc_fin_servicos, cc_fin_rendas, cc_fin_cap_bras, cc_fin_cap_ext | E16: Yes | F16: 5b. Contracted FX (bank-client movement)
A17: Total reserves and by component (FX securities, deposits, IMF, SDR, gold, other assets) | B17: macro_brasil.cmb_reservas_bc | C17: monthly | E17: Yes | F17: 6. International reserves and BCB intervention
A18: Reserves — total and liquidity concept | B18: macro_brasil.cmb_reservas_bc | C18: daily | E18: Yes | F18: 6. International reserves and BCB intervention
A19: Banks' net FX spot position | B19: macro_brasil.cmb_reservas_bc | C19: monthly | E19: Yes | F19: 6. International reserves and BCB intervention
A20: BCB FX swap — net position | B20: macro_brasil.cmb_reservas_bc | C20: monthly | E20: Yes | F20: 6. International reserves and BCB intervention
A21: Stock of repo lines/loans/repurchase agreements in FX | B21: macro_brasil.cmb_reservas_bc | C21: monthly | E21: Yes | F21: 6. International reserves and BCB intervention
A22: BCB interventions (spot, forwards, FX loans/repos, repo lines) — only days with actual intervention | B22: macro_brasil.cmb_reservas_bc | C22: daily (sparse) | E22: Yes | F22: 6. International reserves and BCB intervention
A23: Real (broad) and nominal (broad) REER — Brazil, Mexico, Chile, Colombia | B23: macro_international.cmb_reer | C23: 1994 → today (BIS, full history) | E23: Yes | F23: 7. Real effective exchange rate (REER)
A24: Open interest, net/long/short positioning of "leveraged money" and non-reportables | B24: macro_international.cmb_cot_fx · open_interest, lev_long, lev_short, lev_net, nonrept_long, nonrept_short | C24: BRL and MXN, weekly (Tuesdays), 2010 → today | E24: Yes | F24: 8. Speculative positioning (FX futures)
A25: IPCA (28 series, incl. cores) | B25: macro_brasil.inflc_agregados | E25: Yes | F25: 9. Inflation differential and market expectations | G25: 1980 → today
A26: Focus expectations — IPCA 12m/24m, IGP-M, Selic | B26: macro_brasil.expc_focus | E26: Yes | F26: 9. Inflation differential and market expectations | G26: 2001 → today Mr. Paulo suggestion
A27: US CPI (via FRED, consumed inside the differentials calculation) | B27: macro_international.diferenciais_juros (cpi_12m_us) | E27: Yes | F27: 9. Inflation differential and market expectations | G27: ~36m rolling
A28: Ex-ante interest rate differentials (Focus × Fed Funds futures/OIS) | D28: High | E28: No | F28: 2. Interest rate differential (carry) | G28: Ex-ante differentials (based on expectations, not realized inflation) not implemented yet — see the pending item in analytics/brasil/exchange_rate/CLAUDE.md, uses macro_brasil.expc_focus (Focus) on the BR side and FRED (FF{m} futures/OIS, MICH/T5YIE) on the US side.
A29: CEP/CBE granularity of the financial FX flow | D29: Medium | E29: No | F29: 5a. Registered FX flow (BCB Nota Cambial) | G29: Script: domain/db/brasil/bcb/cmb_fluxo_cambial.py. Coverage: 2003 → today. Gaps: CEP/CBE sub-items of the financial flow (finer granularity, published in the weekly Nota Cambial) — candidate SGS codes (24372–24376) unconfirmed. Commercial balance (24366) timed out during research — can be derived as comercial_entrada − comercial_saida if needed.
A30: Wire cmb_ptax into the analysis agent's snapshot (agent_data.py) | D30: Medium | E30: No | F30: 1. Spot price | G30: Why it matters: the dependent variable — every other category in this inventory exists to explain moves in this one series. Script: domain/db/brasil/bcb/cmb_ptax.py. Daily series — historical load chunks by year (BCB API rejects windows > 10 years for daily series, confirmed via 406 response). Remaining gap: the analysis agent (analytics/brasil/exchange_rate/agent_data.py) hasn't been updated yet to pull cmb_ptax into its snapshot — the data exists but isn't wired into the agent's output.
A31: Cupom cambial + B3 futures (requires Bloomberg access) | D31: Low | E31: No | F31: 2. Interest rate differential (carry) | G31: Cupom cambial (DDI/FRC curve) and B3 futures (DOL/WDO) — deferred, requires Bloomberg access (blpapi/xbbg).
A32: REER/COT for EM peers beyond BR/MX/CL/CO | D32: Low | E32: No | F32: 7. Real effective exchange rate (REER) | G32: Only 4 LatAm countries (BR/MX/CL/CO) — no coverage of other relevant EM peers for comparison (e.g., Turkey, South Africa, India) or developed-market peers.
A33: Options-based positioning data (skew, risk reversal) | D33: Low | E33: No | F33: 8. Speculative positioning (FX futures) | G33: No options-based positioning data (skew, risk reversal) — see the corresponding gap in the bibliography (exchange_rate_bibliography_gaps.md, section 4, FX options and volatility).
A34: Persistent macro_us schema (today only ad hoc FRED in the oráculo) | D34: Low | E34: No | F34: 10. Domestic activity backdrop (context, not FX-specific) | G34: Not an FX category, kept as context. The presentation-layer copy merged in here dropped this section outright, on the grounds that it is general macro backdrop rather than FX-specific data — a fair call for a reading audience, but the series are worth keeping listed for the agent. General macro_brasil series that help contextualize the domestic cycle (relevant for carry/country risk, but not "FX data" per se): atv_ibcbr (monthly GDP proxy), atv_pib, atv_pim (industrial production), atv_pmc/atv_pms (retail/services), mt_pnad (labor market), mt_caged, cred_credito_amplo, cred_credito_familias. Full table in CLAUDE.md. On the US side, activity/inflation data today only exists ad hoc inside analytics/oraculo/us/term_us.py (via FRED) — there's no persistent macro_us schema equivalent to macro_brasil (already logged as a pending item in CLAUDE.md, "Média prioridade — US expandir dados").
A35: No individual commodity prices (iron ore, soybeans, oil) | E35: No | F35: 3. Terms of trade / commodity prices | G35: No individual commodity prices (iron ore, soybeans, oil) — only the aggregate Funcex index. If the agent needs to decompose terms of trade by commodity, there's no data for that today.
A36: real_narrow was excluded from scope (broad basket only). | E36: No | F36: 7. Real effective exchange rate (REER) | G36: real_narrow was excluded from scope (broad basket only).
A37: CLP and COP have no CME futures | E37: No | F37: 8. Speculative positioning (FX futures) | G37: CLP and COP have no CME futures — they don't appear in the TFF report, and there's no equivalent alternative data today.
A38: History not available before 2010 (CFTC returns 404 for 2006–2009). | E38: No | F38: 8. Speculative positioning (FX futures) | G38: History not available before 2010 (CFTC returns 404 for 2006–2009).

Sheet Qual - Monetary Policy
A1: Name | B1: Autor/Company | C1: Date | D1: Importance (1-5) | E1: Do we have it? | F1: Type | G1: Cluster | H1: Why | I1: Comments | J1: File | K1: Ingestion | L1: Ingested on | M1: Extraction | N1: QC flags | O1: Synthesis | P1: Ingestion note
A2: The Role of Monetary Policy | B2: Friedman, M. | C2: 1968 | D2: 5 | E2: Yes | F2: Paper | G2: #policy_rules_and_credibility | H2: Natural rate; what monetary policy can and cannot do | J2: the_role_monetary_policy (Friedman, 1968) | K2: Ingested | L2: 2026-10-20 | M2: reclean (cleaner change) | O2: Yes
A3: Rules Rather than Discretion: The Inconsistency of Optimal Plans | B3: Kydland, F. & Prescott, E. | C3: 1977 | D3: 5 | E3: Yes | F3: Paper | G3: #policy_rules_and_credibility | H3: Time inconsistency: discretion produces inflation bias | J3: time_inconsistency_optimal_plans (Kydland & Prescott, 1977) | K3: Ingested | L3: 2026-10-20 | M3: reclean (cleaner change) | O3: Yes
A4: A Positive Theory of Monetary Policy in a Natural Rate Model | B4: Barro, R. & Gordon, D. | C4: 1983 | D4: 5 | E4: Yes | F4: Paper | G4: #policy_rules_and_credibility | H4: The workhorse inflation-bias model | J4: positive_theory_monetary_policy (Barro & Gordon, 1983) | K4: Ingested | L4: 2026-10-19 | M4: reclean (cleaner change) | O4: Yes
A5: The Optimal Degree of Commitment to an Intermediate Monetary Target | B5: Rogoff, K. | C5: 1985 | D5: 5 | E5: Yes | F5: Paper | G5: #policy_rules_and_credibility | H5: The conservative central banker | I5: PDF acquired (JSTOR copy). | J5: optimal_commitment_intermediate_target (Rogoff, 1985) | K5: Ingested | L5: 2026-10-20 | M5: reclean (cleaner change) | O5: Yes
A6: Central Bank Strategy, Credibility, and Independence: Theory and Evidence (selected chapters) | B6: Cukierman, A. | C6: 1992 | D6: 4 | E6: Dropped | F6: Book | G6: #policy_rules_and_credibility | H6: Canonical synthesis of time-inconsistency theory with the empirical central bank independence (CBI) indices still used in cross-country studies today. Recommended chapters: the introductory theoretical chapter formalizing commitment/discretion, plus the chapter introducing the legal-independence index (LVAU/LVAW) - confirm exact chapter numbers against the table of contents on acquisition. | I6: Dropped 2026-10-07: Theory covered by Rogoff, Walsh and Barro-Gordon; the CBI index matters only for cross-country work
A7: Discretion versus Policy Rules in Practice | B7: Taylor, J. | C7: 1993 | D7: 5 | E7: Yes | F7: Paper | G7: #policy_rules_and_credibility | H7: The Taylor rule | J7: taylor_rule (Taylor, 1993) | K7: Ingested | L7: 2026-10-20 | M7: reclean (cleaner change) | O7: Yes
A8: Optimal Contracts for Central Bankers | B8: Walsh, C. | C8: 1995 | D8: 5 | E8: Yes | F8: Paper | G8: #policy_rules_and_credibility | H8: Inflation bias solved by a performance contract | I8: Acquired PDF is scanned/image-only, no text layer (confirmed via embedded /Image objects, not corruption) - needs actual reading/OCR when processing, not pdftotext/grep. | J8: optimal_contracts_central_bankers (Walsh, 1995) | K8: Ingested | L8: 2026-10-20 | M8: reclean (cleaner change) | O8: Yes
A9: Staggered Prices in a Utility-Maximizing Framework | B9: Calvo, G. | C9: 1983 | D9: 5 | E9: Yes | F9: Paper | G9: #new_keynesian_transmission | H9: The microfoundation of price stickiness | J9: staggered_prices (Calvo, 1983) | K9: Ingested | L9: 2026-10-19 | M9: default | O9: Yes
A10: The Science of Monetary Policy: A New Keynesian Perspective | B10: Clarida, R., Gali, J. & Gertler, M. | C10: 1999 | D10: 5 | E10: Yes | F10: Paper | G10: #new_keynesian_transmission | H10: The 3-equation NK model as the standard framework | I10: Acquired PDF text layer is Caesar-shift-encoded (font-encoding quirk of the source site, not a wrong file - verified by decoding the opening line). Wont extract cleanly with plain pdftotext. | J10: science_of_monetary_policy (Clarida, Gali & Gertler, 1999) | K10: Ingested | L10: 2026-10-20 | M10: reclean (cleaner change) | O10: Yes
A11: Interest and Prices: Foundations of a Theory of Monetary Policy (selected chapters) | B11: Woodford, M. | C11: 2003 | D11: 5 | E11: Dropped | F11: Book | G11: #new_keynesian_transmission | H11: THE modern graduate-level reference on interest-rate-rule-based monetary policy. Recommended: Ch. 1 ('The Return of Monetary Rules,' accessible manifesto) + the commitment-vs-discretion / optimal-rules chapter (Ch. 7 or 8 depending on edition - confirm against ToC). | I11: Do not find Dropped 2026-10-07: Covered for this agent by Galí (2015) ch. 3-5 and Clarida-Galí-Gertler (1999)
A12: Monetary Policy, Inflation, and the Business Cycle (2nd ed.), Ch. 2 - A Classical Monetary Model | B12: Gali, J. | C12: 2015 | D12: 3 | E12: Yes | F12: Textbook chapter | G12: #new_keynesian_transmission | H12: Supporting: the flexible-price benchmark the NK model departs from | J12: classical_monetary_model_ch2 (Gali, 2015) | K12: Ingested | L12: 2026-10-20 | M12: reclean (cleaner change) | O12: Yes
A13: Monetary Policy, Inflation, and the Business Cycle (2nd ed.), Ch. 3 - The Basic New Keynesian Model | B13: Gali, J. | C13: 2015 | D13: 5 | E13: Yes | F13: Textbook chapter | G13: #new_keynesian_transmission | H13: Core: the basic NK model (IS curve, Phillips curve, policy rule) | J13: basic_nk_model_ch3 (Gali, 2015) | K13: Ingested | L13: 2026-10-20 | M13: reclean (cleaner change) | O13: Yes
A14: Monetary Policy, Inflation, and the Business Cycle (2nd ed.), Ch. 4 - Monetary Policy Design in the Basic New Keynesian Model | B14: Gali, J. | C14: 2015 | D14: 5 | E14: Yes | F14: Textbook chapter | G14: #new_keynesian_transmission | H14: Core: optimal policy and simple rules in the basic NK model | J14: monetary_policy_design_nk_ch4 (Gali, 2015) | K14: Ingested | L14: 2026-10-20 | M14: reclean (cleaner change) | O14: Yes
A15: Monetary Policy, Inflation, and the Business Cycle (2nd ed.), Ch. 5 - Monetary Policy Tradeoffs: Discretion versus Commitment | B15: Gali, J. | C15: 2015 | D15: 4 | E15: Yes | F15: Textbook chapter | G15: #new_keynesian_transmission | H15: Discretion vs. commitment, cost-push tradeoffs | J15: discretion_vs_commitment_ch5 (Gali, 2015) | K15: Ingested | L15: 2026-10-20 | M15: reclean (cleaner change) | O15: Yes
A16: Monetary Policy, Inflation, and the Business Cycle (2nd ed.), Ch. 6 - A Model with Sticky Wages and Prices | B16: Gali, J. | C16: 2015 | D16: 3 | E16: Yes | F16: Textbook chapter | G16: #new_keynesian_transmission | H16: Supporting: wage rigidity added to the NK model | J16: sticky_wages_prices_ch6 (Gali, 2015) | K16: Ingested | L16: 2026-10-20 | M16: reclean (cleaner change) | O16: Yes
A17: Monetary Policy, Inflation, and the Business Cycle (2nd ed.), Ch. 7 - Unemployment in the New Keynesian Model | B17: Gali, J. | C17: 2015 | D17: 3 | E17: Yes | F17: Textbook chapter | G17: #new_keynesian_transmission | H17: Supporting: unemployment in the NK model | J17: unemployment_nk_model_ch7 (Gali, 2015) | K17: Ingested | L17: 2026-10-20 | M17: reclean (cleaner change) | O17: Yes
A18: Monetary Policy, Inflation, and the Business Cycle (2nd ed.), Ch. 8 - Monetary Policy in the Open Economy | B18: Gali, J. | C18: 2015 | D18: 4 | E18: Yes | F18: Textbook chapter | G18: #new_keynesian_transmission | H18: Open economy: the small open economy NK model, exchange-rate pass-through | J18: open_economy_monetary_policy_ch8 (Gali, 2015) | K18: Ingested | L18: 2026-10-20 | M18: reclean (cleaner change) | O18: Yes
A19: Monetary Policy and Exchange Rate Volatility in a Small Open Economy | B19: Gali, J. & Monacelli, T. | C19: 2005 | D19: 5 | E19: Yes | F19: Paper | G19: #new_keynesian_transmission | H19: The open-economy NK model; bridge to exchange rate | J19: nk_small_open_economy (Gali & Monacelli, 2005) | K19: Ingested | L19: 2026-10-20 | M19: reclean (cleaner change) | O19: Yes
A20: Inflation Forecast Targeting: Implementing and Monitoring Inflation Targets | B20: Svensson, L. | C20: 1997 | D20: 5 | E20: Yes | F20: Paper | G20: #inflation_targeting_regimes | H20: Forecast targeting — the Copom's own logic: the projection at the relevant horizon decides the rate | J20: inflation_forecast_targeting (Svensson, 1997) | K20: Ingested | L20: 2026-10-20 | M20: reclean (cleaner change) | O20: Yes
A21: Inflation Targeting: Lessons from the International Experience (selected chapters) | B21: Bernanke, B., Laubach, T., Mishkin, F. & Posen, A. | C21: 1999 | D21: 5 | E21: Dropped | F21: Book | G21: #inflation_targeting_regimes | H21: The definitive early cross-country study of inflation targeting adoption and design choices. Recommended: Ch. 1 ('The Rationale for Inflation Targets') + the concluding synthesis chapter - confirm exact chapter number. | I21: Do not find Dropped 2026-10-07: Covered by Svensson (1997), Mishkin (2000) and the Brazil IT papers
A22: Inflation Targeting in Emerging Market Countries | B22: Mishkin, F. | C22: 2000 | D22: 4 | E22: Yes | F22: Paper | G22: #inflation_targeting_regimes | H22: IT under EM conditions (pass-through, weaker institutions) | J22: inflation_targeting_em (Mishkin, 2000) | K22: Ingested | L22: 2026-10-20 | M22: reclean (cleaner change) | O22: Yes
A23: Inflation Targeting (Handbook of Monetary Economics vol. 3B) | B23: Svensson, L. | C23: 2010 | D23: 4 | E23: Yes | F23: Handbook chapter | G23: #inflation_targeting_regimes | H23: The mature version of the 1997 paper: flexible IT, horizon, communication of the projected path | I23: Acquisition priority: low Suggested file: inflation_targeting_handbook (Svensson, 2010).pdf Where to get it: NBER WP 16654 | J23: inflation_targeting_handbook (Svensson, 2010) | K23: Ingested | L23: 2026-10-20 | M23: reclean (cleaner change) | O23: Yes
A24: Credit, Money, and Aggregate Demand | B24: Bernanke, B. & Blinder, A. | C24: 1988 | D24: 4 | E24: Yes | F24: Paper | G24: #transmission_channels_financial_frictions | H24: The bank-lending channel | J24: credit_money_aggregate_demand (Bernanke & Blinder, 1988) | K24: Ingested | L24: 2026-10-20 | M24: reclean (cleaner change) | O24: Yes
A25: Inside the Black Box: The Credit Channel of Monetary Policy Transmission | B25: Bernanke, B. & Gertler, M. | C25: 1995 | D25: 5 | E25: Yes | F25: Paper | G25: #transmission_channels_financial_frictions | H25: The credit channel, accessible statement | J25: credit_channel_transmission (Bernanke & Gertler, 1995) | K25: Ingested | L25: 2026-10-20 | M25: reclean (cleaner change) | O25: Yes
A26: The Financial Accelerator in a Quantitative Business Cycle Framework | B26: Bernanke, B., Gertler, M. & Gilchrist, S. | C26: 1999 | D26: 5 | E26: Yes | F26: Handbook chapter | G26: #transmission_channels_financial_frictions | H26: Balance-sheet amplification of policy | I26: Copy in raw_pdf is the Handbook of Macroeconomics chapter (Northwestern course page), with an OCR text layer: prose reads, equations are garbled. Replaced the NBER WP 6455 scan, which had no text layer, on 2026-10-19. | J26: financial_accelerator (Bernanke, Gertler & Gilchrist, 1999) | K26: Ingested | L26: 2026-10-20 | M26: reclean (cleaner change) | O26: Yes
A27: Transmission Lags of Monetary Policy: A Meta-Analysis (IJCB) | B27: Havranek, T. & Rusnak, M. | C27: 2013 | D27: 3 | E27: Yes | F27: Paper | G27: #transmission_channels_financial_frictions | H27: How long the Selic takes to reach prices — the basis for the "relevant horizon" and the memo's 1-year and 2-3-year horizons | I27: Acquisition priority: medium Suggested file: transmission_lags_meta_analysis (Havranek & Rusnak, 2013).pdf Where to get it: Czech National Bank working-paper version; IJCB is open access (ijcb.org) | J27: transmission_lags_meta_analysis (Havranek & Rusnak, 2013) | K27: Ingested | L27: 2026-10-20 | M27: reclean (cleaner change) | O27: Yes
A28: It's Baaack: Japan's Slump and the Return of the Liquidity Trap | B28: Krugman, P. | C28: 1998 | D28: 5 | E28: Yes | F28: Paper | G28: #unconventional_policy_zlb | H28: The liquidity trap revived | J28: liquidity_trap_japan (Krugman, 1998) | K28: Ingested | L28: 2026-10-20 | M28: reclean (cleaner change) | O28: Yes
A29: The Zero Bound on Interest Rates and Optimal Monetary Policy | B29: Eggertsson, G. & Woodford, M. | C29: 2003 | D29: 5 | E29: Yes | F29: Paper | G29: #unconventional_policy_zlb | H29: Optimal policy at the ZLB; origin of forward guidance as a tool | J29: zero_bound_optimal_policy (Eggertsson & Woodford, 2003) | K29: Ingested | L29: 2026-10-20 | M29: reclean (cleaner change) | O29: Yes
A30: Monetary Policy Alternatives at the Zero Bound: An Empirical Assessment | B30: Bernanke, B., Reinhart, V. & Sack, B. | C30: 2004 | D30: 4 | E30: Yes | F30: Paper | G30: #unconventional_policy_zlb | H30: The menu of alternatives later used in 2008-15 | J30: zero_bound_alternatives (Bernanke, Reinhart & Sack, 2004) | K30: Ingested | L30: 2026-10-20 | M30: reclean (cleaner change) | O30: Yes
A31: A Model of Unconventional Monetary Policy | B31: Gertler, M. & Karadi, P. | C31: 2011 | D31: 4 | E31: Yes | F31: Paper | G31: #unconventional_policy_zlb | H31: Central-bank balance-sheet policy | J31: unconventional_policy_model (Gertler & Karadi, 2011) | K31: Ingested | L31: 2026-10-20 | M31: reclean (cleaner change) | O31: Yes
A32: Dilemma not Trilemma: The Global Financial Cycle and Monetary Policy Independence | B32: Rey, H. | C32: 2013 | D32: 5 | E32: Yes | F32: Paper | G32: #global_spillovers_em_autonomy | H32: The global financial cycle limits EM autonomy even under a float | J32: dilemma_not_trilemma (Rey, 2013) | K32: Ingested | L32: 2026-10-20 | M32: reclean (cleaner change) | O32: Yes
A33: U.S. Monetary Policy and the Global Financial Cycle | B33: Miranda-Agrippino, S. & Rey, H. | C33: 2020 | D33: 4 | E33: Yes | F33: Paper | G33: #global_spillovers_em_autonomy | H33: Quantifies the Fed's spillover | J33: us_monetary_policy_global_cycle (Miranda-Agrippino & Rey, 2020) | K33: Ingested | L33: 2026-10-20 | M33: reclean (cleaner change) | O33: Yes
A34: Trilemma and Trade-offs: Living with Financial Globalization | B34: Obstfeld, M. | C34: 2015 | D34: 4 | E34: Yes | F34: Paper | G34: #global_spillovers_em_autonomy | H34: The counterpoint: floating plus tools still buys autonomy | J34: trilemma_tradeoffs (Obstfeld, 2015) | K34: Ingested | L34: 2026-10-20 | M34: reclean (cleaner change) | O34: Yes
A35: U.S. Monetary Policy and International Risk Spillovers (Jackson Hole) | B35: Kalemli-Özcan, Ş. | C35: 2019 | D35: 4 | E35: Yes | F35: Paper | G35: #global_spillovers_em_autonomy | H35: The Fed reaches EMs through the risk premium, not the rate differential — the channel that makes UIP fail in the BRL | I35: Acquisition priority: medium Suggested file: us_policy_international_risk_spillovers (Kalemli-Ozcan, 2019).pdf Where to get it: NBER WP 26297 / Kansas City Fed symposium page | J35: us_policy_international_risk_spillovers (Kalemli-Ozcan, 2019) | K35: Ingested | L35: 2026-10-20 | M35: reclean (cleaner change) | O35: Yes
A36: Two Targets, Two Instruments (IMF SDN 12/01) | B36: Ostry, J., Ghosh, A. & Chamon, M. | C36: 2012 | D36: 4 | E36: Yes | F36: Paper | G36: #global_spillovers_em_autonomy | H36: Rate vs. FX intervention under IT: the instrument choice in S4. Coordinate with the exchange-rate bibliography, which owns the capital-controls side | I36: Acquisition priority: medium Suggested file: two_targets_two_instruments (Ostry, Ghosh & Chamon, 2012).pdf Where to get it: imf.org — manual download (see the IMF note below) imf.org refuses scripted downloads: save the PDF from a browser into raw_pdf/ | J36: two_targets_two_instruments (Ostry, Ghosh & Chamon, 2012) | K36: Ingested | L36: 2026-10-20 | M36: reclean (cleaner change)
A37: Systematic Monetary Policy and the Forward Premium Puzzle (BIS WP 396) | B37: Tambakis, D. & Tarashev, N. | C37: 2012 | D37: 3 | E37: Yes | F37: Paper | G37: #global_spillovers_em_autonomy | H37: The policy rule as an explanation of UIP failure — shared with exchange rate | J37: systematic_monetary_policy_forward_premium_puzzle (Tambakis & Tarashev, 2012) | K37: Ingested | L37: 2026-10-20 | M37: reclean (cleaner change)
A38: Monetary policy transmission to exchange rates: the role of currency carry trades (BIS Bulletin 124) | B38: Bank for International Settlements | C38: 2026 | D38: 3 | E38: Yes | F38: Paper | G38: #global_spillovers_em_autonomy | H38: Policy → FX through carry positioning | J38: monetary_policy_exchange_rates (BIS, 2026) | K38: Ingested | L38: 2026-10-20 | M38: reclean (cleaner change) | O38: Yes
A39: Implementing Inflation Targeting in Brazil | B39: Bogdanski, J., Tombini, A. & Werlang, S. | C39: 2000 | D39: 5 | E39: Yes | F39: Paper | G39: #brazil_monetary_policy | H39: The regime's founding design | J39: implementing_it_brazil (Bogdanski, Tombini & Werlang, 2000) | K39: Ingested | L39: 2026-10-20 | M39: reclean (cleaner change) | O39: Yes
A40: Inflation Targeting in Brazil: Lessons and Challenges | B40: Minella, A., Freitas, P.S., Goldfajn, I. & Muinhos, M.K. | C40: 2002 | D40: 4 | E40: Yes | F40: Paper | G40: #brazil_monetary_policy | H40: The regime's early progress report | J40: it_lessons_and_challenges (Minella et al., 2002) | K40: Ingested | L40: 2026-10-20 | M40: reclean (cleaner change) | O40: Yes
A41: Inflation Targeting in Brazil: Constructing Credibility under Exchange Rate Volatility | B41: Minella, A., Freitas, P.S., Goldfajn, I. & Muinhos, M.K. | C41: 2003 | D41: 5 | E41: Yes | F41: Paper | G41: #brazil_monetary_policy | H41: Credibility built through the 2002 FX shock; an early estimated reaction function | J41: it_credibility_fx_volatility (Minella et al., 2003) | K41: Ingested | L41: 2026-10-20 | M41: reclean (cleaner change) | O41: Yes
A42: Fiscal Dominance and Inflation Targeting: Lessons from Brazil | B42: Blanchard, O. | C42: 2004 | D42: 5 | E42: Yes | F42: Paper | G42: #brazil_monetary_policy | H42: When a hike depreciates the BRL through the fiscal/risk channel | J42: fiscal_dominance_it_brazil (Blanchard, 2004) | K42: Ingested | L42: 2026-10-20 | M42: reclean (cleaner change) | O42: Yes
A43: Inflation Targeting and Debt: Lessons from Brazil | B43: Favero, C. & Giavazzi, F. | C43: 2004 | D43: 4 | E43: Yes | F43: Paper | G43: #brazil_monetary_policy | H43: The empirical companion to Blanchard | J43: it_and_debt_brazil (Favero & Giavazzi, 2004) | K43: Ingested | L43: 2026-10-20 | M43: reclean (cleaner change) | O43: Yes
A44: Comparing Equilibrium Real Interest Rates: Different Approaches to Measure Brazilian Rates | B44: Muinhos, M. & Nakane, M. | C44: 2006 | D44: 3 | E44: Yes | F44: Paper | G44: #brazil_monetary_policy | H44: Early Brazil neutral-rate estimates; superseded on the level by cluster 12 | J44: neutral_rate_brazil (Muinhos & Nakane, 2006) | K44: Ingested | L44: 2026-10-20 | M44: reclean (cleaner change)
A45: Credit, Interest, and Jurisdictional Uncertainty: Conjectures on the Case of Brazil | B45: Arida, P., Bacha, E. & Lara-Resende, A. | C45: 2005 | D45: 4 | E45: Yes | F45: Book chapter | G45: #brazil_monetary_policy | H45: The classic thesis on why Brazil's rates are so high. Same volume holds the published versions of Blanchard and Favero-Giavazzi | I45: Acquisition priority: medium Suggested file: credit_interest_jurisdictional_uncertainty (Arida, Bacha & Lara-Resende, 2005).pdf Where to get it: Book chapter; look for the IEPE/Casa das Garças working-paper version | J45: credit_interest_jurisdictional_uncertainty (Arida, Bacha & Lara-Resende, 2005) | K45: Ingested | L45: 2026-10-20 | M45: reclean (cleaner change)
A46: SAMBA: Stochastic Analytical Model with a Bayesian Approach (BCB WP 239 (+ the updated version, BCB WP 578)) | B46: de Castro, M., Gouvea, S., Minella, A., Santos, R. & Souza-Sobrinho, N. | C46: 2011 | D46: 4 | E46: Yes | F46: Paper | G46: #brazil_monetary_policy | H46: The BCB's own DSGE: fiscal surplus target, administered prices, external finance | I46: Acquisition priority: medium Suggested file: samba_dsge_brazil (de Castro et al., 2011).pdf and samba_dsge_brazil_update (BCB WP 578).pdf (confirm authors/year of 578 on acquisition) Where to get it: bcb.gov.br/pec/wps/ingl/wps239.pdf, wps578.pdf | J46: samba_dsge_brazil (de Castro et al., 2011) | K46: Ingested | L46: 2026-10-20 | M46: reclean (cleaner change)
A47: Monetary Policy Channels in Brazil through the Lens of a Semi-Structural Model (Economic Modelling (BCB WP 181, 2009)) | B47: Minella, A. & Souza-Sobrinho, N. | C47: 2013 | D47: 4 | E47: Yes | F47: Paper | G47: #brazil_monetary_policy | H47: Splits Brazil's transmission into household rate, firm rate and FX channels; same family as the model analytics/brasil/structural_model/ replicates | J47: monetary_channels_brazil_semi_structural (Minella & Souza-Sobrinho, 2013) | K47: Ingested | L47: 2026-10-20 | M47: reclean (cleaner change)
A48: The Impact of Monetary Policy on the Exchange Rate: A High Frequency Exchange Rate Puzzle in Emerging Economies (JIMF (BCB WP 259, 2011)) | B48: Kohlscheen, E. | C48: 2014 | D48: 3 | E48: Yes | F48: Paper | G48: #brazil_monetary_policy | H48: Brazil's own evidence for S2: on decision days a hike does not appreciate the BRL | J48: monetary_policy_fx_puzzle_em (Kohlscheen, 2014) | K48: Ingested | L48: 2026-10-20 | M48: reclean (cleaner change)
A49: The Impact of Government-Driven Loans in the Monetary Transmission Mechanism (BCB WP 419) | B49: Bonomo, M. & Martins, B. | C49: 2016 | D49: 3 | E49: Yes | F49: Paper | G49: #brazil_monetary_policy | H49: Earmarked credit weakens the credit channel — the "half-power" of the Selic | I49: Acquisition priority: medium Suggested file: directed_credit_monetary_transmission (Bonomo & Martins, 2016).pdf Where to get it: bcb.gov.br/pec/wps/ingl/wps419.pdf | J49: directed_credit_monetary_transmission (Bonomo & Martins, 2016) | K49: Ingested | L49: 2026-10-20 | M49: reclean (cleaner change)
A50: Uncertainty and the Effectiveness of Policy (AER P&P) | B50: Brainard, W. | C50: 1967 | D50: 5 | E50: No | F50: Paper | G50: #reaction_function_and_gradualism | H50: Parameter uncertainty makes the optimal response smaller — the root of gradualism | I50: Acquisition priority: medium Suggested file: uncertainty_policy_effectiveness (Brainard, 1967).pdf Where to get it: JSTOR (paywalled); no free copy checked yet
A51: Monetary Policy Rules and Macroeconomic Stability: Evidence and Some Theory (QJE) | B51: Clarida, R., Galí, J. & Gertler, M. | C51: 2000 | D51: 5 | E51: Yes | F51: Paper | G51: #reaction_function_and_gradualism | H51: The template for estimating a forward-looking reaction function with smoothing; the Taylor principle as a stability condition (S4) | J51: monetary_policy_rules_stability (Clarida, Gali & Gertler, 2000) | K51: Ingested | L51: 2026-10-20 | M51: reclean (cleaner change) | O51: Yes
A52: Monetary Policy Rules Based on Real-Time Data (AER) | B52: Orphanides, A. | C52: 2001 | D52: 5 | E52: Yes | F52: Paper | G52: #reaction_function_and_gradualism | H52: A rule evaluated with revised data is not the rule the central bank followed; real-time output-gap error. The BCB-vs-market gap divergence in the QPC | J52: policy_rules_real_time_data (Orphanides, 2001) | K52: Ingested | L52: 2026-10-20 | M52: reclean (cleaner change) | O52: Yes
A53: Optimal Monetary Policy Inertia (NBER WP 7261) | B53: Woodford, M. | C53: 1999 | D53: 4 | E53: Yes | F53: Paper | G53: #reaction_function_and_gradualism | H53: Why moving in small, predictable steps is optimal under commitment — the Copom's step sizes | I53: Working-paper version of "Optimal Interest-Rate Smoothing" (REStud 2003, paywalled), which is the published article. | J53: optimal_monetary_policy_inertia (Woodford, 1999) | K53: Ingested | L53: 2026-10-20 | M53: reclean (cleaner change) | O53: Yes
A54: Monetary Policy Shocks: What Have We Learned and to What End? (Handbook of Macroeconomics 1A) | B54: Christiano, L., Eichenbaum, M. & Evans, C. | C54: 1999 | D54: 5 | E54: Yes | F54: Handbook chapter | G54: #policy_surprises_and_information_effect | H54: VAR identification of policy shocks; the benchmark impulse responses | I54: Acquisition priority: low Suggested file: monetary_policy_shocks_survey (Christiano, Eichenbaum & Evans, 1999).pdf Where to get it: NBER WP 6400 | J54: monetary_policy_shocks_survey (Christiano, Eichenbaum & Evans, 1999) | K54: Ingested | L54: 2026-10-20 | M54: reclean (cleaner change) | O54: Yes
A55: A New Measure of Monetary Shocks: Derivation and Implications (AER) | B55: Romer, C. & Romer, D. | C55: 2004 | D55: 5 | E55: Yes | F55: Paper | G55: #policy_surprises_and_information_effect | H55: Separating the policy decision from the central bank's forecast | I55: Acquisition priority: low Suggested file: new_measure_monetary_shocks (Romer & Romer, 2004).pdf Where to get it: NBER WP 9866 / the authors' Berkeley pages | J55: new_measure_monetary_shocks (Romer & Romer, 2004) | K55: Ingested | L55: 2026-10-20 | M55: reclean (cleaner change) | O55: Yes
A56: Do Actions Speak Louder Than Words? (IJCB) | B56: Gürkaynak, R., Sack, B. & Swanson, E. | C56: 2005 | D56: 5 | E56: Yes | F56: Paper | G56: #policy_surprises_and_information_effect | H56: Two factors in a decision's surprise: the rate and the path signalled. Template for reading the DI curve on a Copom day | I56: Acquisition priority: medium Suggested file: policy_actions_vs_words (Gurkaynak, Sack & Swanson, 2005).pdf Where to get it: IJCB is open access; also Fed FEDS 2004-66 | J56: policy_actions_vs_words (Gurkaynak, Sack & Swanson, 2005) | K56: Ingested | L56: 2026-10-20 | M56: reclean (cleaner change) | O56: Yes
A57: High-Frequency Identification of Monetary Non-Neutrality: The Information Effect (QJE) | B57: Nakamura, E. & Steinsson, J. | C57: 2018 | D57: 5 | E57: Yes | F57: Paper | G57: #policy_surprises_and_information_effect | H57: A hike can carry news about the central bank's view of the economy — the theory behind S2 | J57: information_effect_hf_identification (Nakamura & Steinsson, 2018) | K57: Ingested | L57: 2026-10-20 | M57: reclean (cleaner change) | O57: Yes
A58: Deconstructing Monetary Policy Surprises — The Role of Information Shocks (AEJ: Macro) | B58: Jarociński, M. & Karadi, P. | C58: 2020 | D58: 4 | E58: Yes | F58: Paper | G58: #policy_surprises_and_information_effect | H58: Separates pure policy shocks from information shocks by the sign of the stock-market reaction — a method the agent can apply to S2 | J58: information_shocks_policy_surprises (Jarocinski & Karadi, 2020) | K58: Ingested | L58: 2026-10-20 | M58: reclean (cleaner change) | O58: Yes
A59: Central Bank Communication and Monetary Policy: A Survey of Theory and Evidence (JEL) | B59: Blinder, A., Ehrmann, M., Fratzscher, M., de Haan, J. & Jansen, D.-J. | C59: 2008 | D59: 5 | E59: Yes | F59: Paper | G59: #communication_and_forward_guidance | H59: Why and how communication moves expectations; what evidence there is | J59: central_bank_communication_survey (Blinder et al., 2008) | K59: Ingested | L59: 2026-10-20 | M59: reclean (cleaner change) | O59: Yes
A60: Macroeconomic Effects of Federal Reserve Forward Guidance (BPEA) | B60: Campbell, J., Evans, C., Fisher, J. & Justiniano, A. | C60: 2012 | D60: 5 | E60: Yes | F60: Paper | G60: #communication_and_forward_guidance | H60: Delphic (forecast) vs. Odyssean (commitment) guidance — the distinction for reading the Copom's guidance language | J60: forward_guidance_effects (Campbell et al., 2012) | K60: Ingested | L60: 2026-10-20 | M60: reclean (cleaner change) | O60: Yes
A61: Measuring the Natural Rate of Interest (REStat) | B61: Laubach, T. & Williams, J. | C61: 2003 | D61: 5 | E61: Yes | F61: Paper | G61: #neutral_rate | H61: The canonical r* estimation method (Kalman filter on IS and Phillips curve) | J61: natural_rate_measurement (Laubach & Williams, 2003) | K61: Ingested | L61: 2026-10-20 | M61: reclean (cleaner change) | O61: Yes
A62: Measuring the Natural Rate of Interest: International Trends and Determinants (JIE) | B62: Holston, K., Laubach, T. & Williams, J. | C62: 2017 | D62: 4 | E62: Yes | F62: Paper | G62: #neutral_rate | H62: The same method across countries; the global r* decline | J62: natural_rate_international (Holston, Laubach & Williams, 2017) | K62: Ingested | L62: 2026-10-20 | M62: reclean (cleaner change) | O62: Yes
A63: The Puzzle of Brazil's High Interest Rates (IMF WP 12/62) | B63: Segura-Ubiergo, A. | C63: 2012 | D63: 3 | E63: Yes | F63: Paper | G63: #neutral_rate | H63: Why Brazil's neutral rate is so high: savings, fiscal position, credit segmentation, indexation | I63: Acquisition priority: high Suggested file: high_interest_rates_puzzle_brazil (Segura-Ubiergo, 2012).pdf Where to get it: imf.org/external/pubs/ft/wp/2012/wp1262.pdf — manual download imf.org refuses scripted downloads: save the PDF from a browser into raw_pdf/ | J63: high_interest_rates_puzzle_brazil (Segura-Ubiergo, 2012) | K63: Ingested | L63: 2026-10-20 | M63: reclean (cleaner change) | O63: Yes
A64: Time-Varying Neutral Interest Rate — The Case of Brazil (IMF WP 14/84) | B64: Perrelli, R. & Roache, S. | C64: 2014 | D64: 3 | E64: Yes | F64: Paper | G64: #neutral_rate | H64: A time-varying neutral for Brazil from several models, and what getting it wrong does to the policy prescription | I64: Acquisition priority: high Suggested file: neutral_rate_time_varying_brazil (Perrelli & Roache, 2014).pdf Where to get it: imf.org/external/pubs/ft/wp/2014/wp1484.pdf — manual download imf.org refuses scripted downloads: save the PDF from a browser into raw_pdf/ | J64: neutral_rate_time_varying_brazil (Perrelli & Roache, 2014) | K64: Ingested | L64: 2026-10-20 | M64: reclean (cleaner change) | O64: Yes
A65: Pricing the Term Structure with Linear Regressions (JFE) | B65: Adrian, T., Crump, R. & Moench, E. | C65: 2013 | D65: 4 | E65: Yes | F65: Paper | G65: #term_structure_and_market_pricing | H65: Term-premium decomposition; without it, the Selic path implied by the DI curve carries the premium (S1) | I65: Acquisition priority: medium Suggested file: term_structure_linear_regressions (Adrian, Crump & Moench, 2013).pdf Where to get it: NY Fed Staff Report 340 | J65: term_structure_linear_regressions (Adrian, Crump & Moench, 2013) | K65: Ingested | L65: 2026-10-20 | M65: reclean (cleaner change) | O65: Yes
A66: Decreto nº 3.088/1999 | B66: Brazil (federal law) | C66: 1999 | E66: Yes | F66: Primary legal source | G66: #institutional_framework | H66: Adoption of the inflation-targeting regime | I66: Acquisition priority: medium Suggested file: decreto_3088_1999_metas_inflacao.pdf Where to get it: planalto.gov.br | J66: decreto_3088_metas_inflacao (Brazil, 1999) | K66: Ingested | L66: 2026-10-20 | M66: default | N66: garbled (common-word share 0.035)
A67: Lei Complementar nº 179/2021 | B67: Brazil (federal law) | C67: 2021 | E67: Yes | F67: Primary legal source | G67: #institutional_framework | H67: BCB autonomy, fixed mandates, and the secondary mandate (smooth activity, foster full employment) | I67: Acquisition priority: medium Suggested file: lc_179_2021_autonomia_bcb.pdf Where to get it: planalto.gov.br | J67: lc_179_autonomia_bcb (Brazil, 2021) | K67: Ingested | L67: 2026-10-20 | M67: default | N67: garbled (common-word share 0.022)
A68: Decreto nº 12.079/2024 | B68: Brazil (federal law) | C68: 2024 | E68: Yes | F68: Primary legal source | G68: #institutional_framework | H68: The continuous target (from 2025): breach means six consecutive months outside the band | I68: Acquisition priority: medium Suggested file: decreto_12079_2024_meta_continua.pdf Where to get it: planalto.gov.br | J68: decreto_12079_meta_continua (Brazil, 2024) | K68: Ingested | L68: 2026-10-20 | M68: default | N68: no_text_layer (33% of pages empty — scanned?); garbled (common-word share 0.044)
A69: Comunicado (COPOM Statement) | B69: Banco Central do Brasil | C69: Recurring, ~8/year | E69: Yes | F69: Primary source (recurring) | G69: #brazil_policy_communication | H69: Same day as each COPOM meeting. Very short (roughly one page): the Selic decision itself plus a brief summary of the immediate rationale and balance of risks. | I69: In the vault through the Copom ETL (pm_copom_projecoes.run()), not through /ingest: obsidian/monetary_policy/clean_md/central_bank/ — all comunicados and atas, the RPM in full for the last 3 years; the full RPM history is pending (SISTEMA_AGENTES II.III.iv).
A70: Ata do Copom (COPOM Minutes) | B70: Banco Central do Brasil | C70: Recurring, ~6 business days after each meeting | E70: Yes | F70: Primary source (recurring) | G70: #brazil_policy_communication | H70: Full deliberation: detailed scenario discussion, balance-of-risks analysis, forward guidance language, vote record. Retention window and ingestion mechanism explicitly deferred to a later session. | I70: In the vault through the Copom ETL (pm_copom_projecoes.run()), not through /ingest: obsidian/monetary_policy/clean_md/central_bank/ — all comunicados and atas, the RPM in full for the last 3 years; the full RPM history is pending (SISTEMA_AGENTES II.III.iv).
A71: Relatorio de Politica Monetaria (RPM, formerly Relatorio de Inflacao) | B71: Banco Central do Brasil | C71: Recurring, quarterly | E71: Yes | F71: Primary source (recurring) | G71: #brazil_policy_communication | H71: Full projection exercise: conditional and unconditional inflation projections, fan charts (leques), GDP projections, scenario assumptions (FX, oil, Selic path), special-topic boxes. | I71: In the vault through the Copom ETL (pm_copom_projecoes.run()), not through /ingest: obsidian/monetary_policy/clean_md/central_bank/ — all comunicados and atas, the RPM in full for the last 3 years; the full RPM history is pending (SISTEMA_AGENTES II.III.iv).
A72: Brazilian Macroeconomic Dynamics Redux: Shocks, Frictions, and Unemployment in SAMBA Model (BCB WP 578) | B72: Fasolo, A., Araújo, E., Jorge, M., Kornelius, A. & Marinho, L. | C72: 2023 | D72: 4 | E72: Yes | F72: Paper | G72: #brazil_monetary_policy | H72: The current version of the BCB's own DSGE: SAMBA extended with labour-market frictions and unemployment and re-estimated; the up-to-date reference for how the BCB models transmission and decomposes shocks | I72: BCB WP 578 (March 2023). Update of SAMBA (de Castro et al., 2011), which has its own row | J72: samba_dsge_brazil_update (Fasolo et al., 2023) | K72: Ingested | L72: 2026-10-20 | M72: reclean (cleaner change)

Sheet Quant - Monetary Policy
A1: Name | B1: Source | C1: Date | D1: Importance | E1: Do we have it? | F1: Category | G1: Comments
A2: Selic, Fed Funds (raw) | B2: macro_international.diferenciais_juros · selic, fed_funds | E2: Yes | F2: 2. Interest rate differentials (carry)
A3: Nominal and real ex-post differentials | B3: macro_international.diferenciais_juros · diferencial_nominal, real_br_ex_post, real_us_ex_post, diferencial_real | E3: Yes | F3: 2. Interest rate differentials (carry)
A4: Focus survey — Selic median/mean expectations | B4: macro_brasil.expc_focus | E4: Yes | F4: 3. Market-implied rate expectations | G4: indicador = 'Selic', various horizons; 2001 → today
A5: Focus survey — IPCA, IGP-M expectations | B5: macro_brasil.expc_focus | E5: Yes | F5: 3. Market-implied rate expectations | G5: same table, other indicador values
A6: Real rate ex-post (Selic − realized IPCA 12m) | B6: macro_international.diferenciais_juros | E6: Yes | F6: 4. Real interest rate & neutral rate (r*) | G6: real_br_ex_post
A7: Fed Funds (raw, as part of the differential calc) | B7: macro_international.diferenciais_juros · fed_funds | E7: Yes | F7: 7. Global monetary conditions
A8: No COPOM decision history table (meeting-level rate changes, votes) | D8: High | E8: No | F8: 1. Policy rate & COPOM decision history | G8: There is no dedicated table recording COPOM decisions as discrete events (meeting date, rate before/after, change in bps, vote count/dissent). The Selic level only exists today embedded inside macro_international.diferenciais_juros (series selic, sourced from BCB SGS 432) as a continuous monthly series for computing rate differentials — it was never built to answer "what did COPOM actually decide, and how divided was the committee, at each meeting." Impact: without this, the agent can't backtest a reaction function against actual historical decisions, or characterize dissent/unanimity patterns (directly relevant to reading credibility, per the Barro-Gordon/Rogoff literature already in the bibliography). Possible approach: a copom_decisions table — (meeting_date, selic_before, selic_after, change_bps, votes_for, votes_against, unanimous) — sourced from BCB SGS 432 (which already carries COPOM meeting dates, not calendar dates) plus vote counts parsed from the Ata once §8 of the bibliography is acquired. No script built yet.
A9: No neutral/equilibrium real rate (r*) — no proxy, no model estimate | D9: High | E9: No | F9: 4. Real interest rate & neutral rate (r*) | G9: No neutral/equilibrium real rate (r*) estimate at all. This is precisely the gap the Muinhos & Nakane (2006) bibliography candidate addresses theoretically, but there's no data pipeline — no market-based proxy (e.g. long NTN-B real yields) and no BCB model-based estimate (which the RPM publishes as part of its projection exercise, once §8 of the bibliography is acquired). Without r*, the agent has no denominator for "how tight is policy," which is arguably the single most load-bearing number for a synthesis agent to have.
A10: Ex-ante real/nominal rate differentials not computed (inputs already exist in expc_focus, just not combined) | D10: Medium | E10: No | F10: 2. Interest rate differentials (carry) | G10: Ex-ante differentials (Focus-based) not implemented — see the pending item in analytics/brasil/exchange_rate/CLAUDE.md. For monetary policy specifically, selic_ex_ante (Focus Selic EOP 12m, already sitting in macro_brasil.expc_focus) is close to the single most directly relevant missing series: it's the market's own forward-looking read on the same thing the agent is trying to compute.
A11: No inflation target regime parameter table (target/band/horizon history) | D11: Medium | E11: No | F11: 6. Inflation target regime parameters | G11: No table records the history of the target itself: the numeric target, tolerance band width, and target horizon, as set by CMN (Conselho Monetário Nacional) resolutions, which have changed several times since 1999 (target level, band width, and the horizon convention have all been revised over the years). This is small, slow-moving, easy to build (a short lookup table by year) but currently doesn't exist anywhere — without it, the agent can't correctly compute an inflation gap even once it has an inflation forecast, since "the target" isn't a fixed constant across the whole sample.
A12: Full history of diferenciais_juros (same gap as FX inventory, ~36m today) | D12: Medium | E12: No | F12: 2. Interest rate differentials (carry) | G12: History limited to ~36 months by default — needs full extension (Selic since 1996, Fed Funds since 1954).
A13: No DI futures curve (Bloomberg-dependent) | D13: Low | E13: No | F13: 3. Market-implied rate expectations | G13: No DI futures curve (B3) — the market-priced, real-time-updating implied Selic path, as opposed to the survey-based Focus median. This is the same Bloomberg-dependent gap already flagged as a pending item in analytics/brasil/exchange_rate/CLAUDE.md ("Cupom cambial + B3 FX futures", requires blpapi/xbbg). Focus is a usable substitute today but updates weekly and reflects survey consensus, not tradeable pricing.
A14: Global policy-rate context limited to Fed Funds only | D14: Low | E14: No | F14: 7. Global monetary conditions | G14: Gaps: only the Fed is covered. No broader global policy-rate context (ECB, other EM central banks) for situating BCB within the "global financial cycle" framing central to the Rey (2013) / Obstfeld (2015) debate in the bibliography's #global_spillovers_em_autonomy cluster. Low priority unless a specific cross-country comparison becomes necessary.
A15: No ex-ante real rate (Selic − expected IPCA, which is the theoretically correct measure of how restrictive/expansionary | E15: No | F15: 4. Real interest rate & neutral rate (r*) | G15: No ex-ante real rate (Selic − expected IPCA, which is the theoretically correct measure of how restrictive/expansionary policy actually is right now) — same missing piece as item 2 above (needs Focus IPCA expectations, already available, just not yet combined).
A16: Inflation gap / nowcast at the policy-relevant horizon | E16: Needs agent | F16: Tier 2 — From a future inflation agent | G16: Inflation gap / nowcast at the policy-relevant horizon (the actual forecast-targeting input Svensson's framework calls for)
A17: Core inflation decomposition and diffusion index | E17: Needs agent | F17: Tier 2 — From a future inflation agent | G17: Core inflation decomposition and diffusion index (breadth of price pressure)
A18: Signal on whether inflation expectations are anchored or de-anchoring | E18: Needs agent | F18: Tier 2 — From a future inflation agent | G18: Signal on whether inflation expectations are anchored or de-anchoring (distance of Focus 12m/24m from target, and its trend)
A19: Output gap estimate | E19: Needs agent | F19: Tier 2 — From a future activity agent | G19: Output gap estimate (vs. atv_ibcbr/atv_pib-based potential)
A20: Labor market slack | E20: Needs agent | F20: Tier 2 — From a future activity agent | G20: Labor market slack (unemployment gap vs. NAIRU-type estimate)
A21: Credit growth / credit impulse read | E21: Needs agent | F21: Tier 2 — From a future activity agent | G21: Credit growth / credit impulse read (ties to the #transmission_channels_financial_frictions bibliography cluster — how much of any given Selic move is actually reaching the real economy through credit)
A22: Primary balance and debt trajectory signal | E22: Needs agent | F22: Tier 2 — From a future fiscal agent | G22: Primary balance and debt trajectory signal
A23: A fiscal impulse measure | E23: Needs agent | F23: Tier 2 — From a future fiscal agent | G23: A fiscal impulse measure (is fiscal policy net expansionary or contractionary right now)
A24: A fiscal-dominance / sustainability risk signal — directly operationalizes Blanchard | E24: Needs agent | F24: Tier 2 — From a future fiscal agent | G24: A fiscal-dominance / sustainability risk signal — directly operationalizes Blanchard (2004): is there a regime where hiking Selic further would raise, not lower, medium-term inflation risk through the debt/risk-premium channel?
A25: An FX pass-through estimate | E25: Needs agent | F25: Tier 2 — From the exchange rate agent (already substantially built | G25: An FX pass-through estimate (how much of any BRL move shows up in inflation, and over what horizon)
A26: A REER over/undervaluation signal | E26: Needs agent | F26: Tier 2 — From the exchange rate agent (already substantially built | G26: A REER over/undervaluation signal (already have raw REER in macro_international.cmb_reer; no "gap vs. equilibrium" estimate yet)
... A29: Commodity price cycle read | E29: Needs agent | F29: Tier 2 — From a possible future global/markets agent (not yet scoped at all) | G29: Commodity price cycle read (relevant both to terms of trade and to imported inflation)

Sheet Qual - Economic Activity
A1: Name | B1: Autor/Company | C1: Date | D1: Importance (1-5) | E1: Do we have it? | F1: Type | G1: Cluster | H1: Why | I1: Comments | J1: File | K1: Ingestion | L1: Ingested on | M1: Extraction | N1: QC flags | O1: Synthesis | P1: Ingestion note
A2: Propagation Problems and Impulse Problems in Dynamic Economics | B2: Frisch, R. | C2: 1933 | D2: 5 | E2: No | F2: Paper (book chapter) | G2: #business_cycle_theory_foundations | H2: The founding impulse-propagation distinction — nearly a century later, every business cycle model (RBC, NK-DSGE) is still organized around "what are the shocks" and "what is the propagation mechanism" exactly as Frisch framed it | I2: Suggested file: propagation_impulse_problems (Frisch, 1933).pdf
A3: The Summation of Random Causes as the Source of Cyclic Processes | B3: Slutsky, E. | C3: 1937 | D3: 4 | E3: No | F3: Paper | G3: #business_cycle_theory_foundations | H3: Companion founding result: shows that summing purely random shocks can generate apparently cyclical behavior - the statistical counterpart to Frisch's conceptual framework, and an early warning against reading business cycles as necessarily driven by a single recurring cause
A4: Measuring Business Cycles | B4: Burns, A. & Mitchell, W. | C4: 1946 | D4: 5 | E4: No | F4: Book | G4: #business_cycle_theory_foundations | H4: The empirical/dating tradition - defines a business cycle as a recurring but not periodic sequence of expansion/contraction phases across many series, not a single output series crossing a threshold. Directly the methodological ancestor of NBER's own dating committee and of CODACE (cluster 6), Brazil's equivalent
A5: Understanding Business Cycles | B5: Lucas, R. | C5: 1977 | D5: 5 | E5: No | F5: Paper | G5: #business_cycle_theory_foundations | H5: Lucas's own manifesto for equilibrium business cycle theory - argues cycles should be explained as the equilibrium response of rational agents to shocks, not as market failure; the direct theoretical setup for Kydland-Prescott below. Distinct from Lucas's 1976 policy-evaluation critique already cited in the monetary policy and inflation bibliographies
A6: Time to Build and Aggregate Fluctuations | B6: Kydland, F. & Prescott, E. | C6: 1982 | D6: 5 | E6: No | F6: Paper | G6: #business_cycle_theory_foundations | H6: THE founding Real Business Cycle (RBC) paper - shows technology shocks propagated through a time-to-build investment structure can generate realistic-looking business cycles without any nominal rigidity or policy failure
A7: Real Business Cycles | B7: Long, J. & Plosser, C. | C7: 1983 | D7: 4 | E7: No | F7: Paper | G7: #business_cycle_theory_foundations | H7: The other founding RBC paper, published almost simultaneously with Kydland-Prescott - a multi-sector real model showing comovement across sectors from a common technology shock, without any money or nominal rigidity
A8: Potential GNP: Its Measurement and Significance | B8: Okun, A. | C8: 1962 | D8: 5 | E8: No | F8: Paper | G8: #output_gap_and_potential_output_measurement | H8: The founding statement of the output gap concept itself (alongside Okun's Law, the unemployment-output relationship) — everything in this cluster is downstream of this paper's basic framing | I8: Suggested file: potential_gnp_measurement (Okun, 1962).pdf
A9: Postwar U.S. Business Cycles: An Empirical Investigation | B9: Hodrick, R. & Prescott, E. | C9: 1997 | D9: 5 | E9: No | F9: Paper | G9: #output_gap_and_potential_output_measurement | H9: The canonical citation for the HP filter - the single most-used (and most-criticized, see the well-known "spurious cycle" critique) trend-extraction tool for separating potential output from the cycle; essential to read before using or critiquing any HP-filtered output gap, including the Brazil-specific ones in the local database
A10: The Dynamic Effects of Aggregate Demand and Supply Disturbances | B10: Blanchard, O. & Quah, D. | C10: 1989 | D10: 5 | E10: No | F10: Paper | G10: #output_gap_and_potential_output_measurement | H10: Structural VAR decomposition into permanent (supply) and transitory (demand) shocks - a theory-disciplined alternative to purely statistical filters like HP, and the standard reference for that whole class of output gap methodology
A11: Estimating Potential Output as a Latent Variable | B11: Kuttner, K. | C11: 1994 | D11: 4 | E11: No | F11: Paper | G11: #output_gap_and_potential_output_measurement | H11: Unobserved-components/Kalman-filter approach to potential output - the direct methodological ancestor of the Harvey-Clark method used in the Brazil-specific paper below
A12: Output Gap and GDP in Brazil: A Real-Time Data Analysis | B12: Cusinato, R.T., Minella, A. & Porto Junior, S. | C12: 2010 | D12: 5 | E12: No | F12: Paper | G12: #output_gap_and_potential_output_measurement | H12: The definitive Brazil-specific output-gap methodology comparison - tests HP filter, linear/quadratic trend, and the Harvey-Clark unobserved-components model against real-time (not just final-revision) Brazilian GDP data, finding substantial revision uncertainty across all methods. Directly informs the "no output-gap estimate exists" gap already flagged in monetary_policy_data_inventory.md SS4
A13: Produto Potencial: Conceitos, Metodos de Estimacao e Aplicacao a Economia Brasileira | B13: Souza Junior, J.R.C. | C13: 2005 | D13: 4 | E13: No | F13: Paper | G13: #output_gap_and_potential_output_measurement | H13: The broadest Brazil-specific potential-output survey - combines the production-function method with the HP filter and finds the 2003+ recovery wasn't matched by equivalent potential-output growth; complements Cusinato-Minella-Porto Junior's narrower methodology-comparison focus with a fuller conceptual treatment and a production-function angle that connects directly to cluster 9's productivity work | I13: Also listed under #brazil_productivity_and_potential_growth
A14: Technical Change and the Aggregate Production Function | B14: Solow, R. | C14: 1957 | D14: 5 | E14: No | F14: Paper | G14: #brazil_productivity_and_potential_growth | H14: The founding growth-accounting paper — introduces the "Solow residual," decomposing output growth into capital, labor, and an unexplained residual (total factor productivity). Distinct from Solow (1956, cluster 3), which is the theoretical growth model; this is the empirical measurement companion that everything in this cluster, including the Brazil-specific studies below, is built on | I14: Suggested file: technical_change_aggregate_production_function (Solow, 1957).pdf
A15: Evolucao da Produtividade e do Rendimento do Trabalho | B15: Banco Central do Brasil | C15: 2018 | D15: 4 | E15: No | F15: Paper (report box / special study) | G15: #brazil_productivity_and_potential_growth | H15: BCB's own labor-productivity study — measures value-added per worker (VAB/PO) for 2012Q1-2018Q3 in the sectors most tied to the business cycle, finds a 9.5% cumulative decline driven mostly by within-sector (not reallocation) effects, and compares it against real labor income growth | I15: Suggested file: evolucao_produtividade_rendimento_trabalho (BCB, 2018).pdf
A16: Nota Metodologica dos Indicadores Anuais de Produtividade Total dos Fatores no Brasil desde a Decada de 1980 | B16: Veloso, F., Matos, S. & Peruchetti, P. | C16: 2020 | D16: 5 | E16: No | F16: Paper (methodological note) | G16: #brazil_productivity_and_potential_growth | H16: This closes the gap flagged in the previous pass — the actual aggregate-TFP-for-Brazil methodology note, filling exactly the hole BCB's own material (labor productivity only, EE027/2018 above) doesn't cover. Built to address a specific problem the authors identify explicitly: existing Brazilian TFP estimates were often not public or not documented in enough detail to replicate | I16: Suggested file: ptf_brasil_nota_metodologica (Veloso, Matos & Peruchetti, 2020a).pdf
A17: Produtividade Total dos Fatores no Brasil: Uma Visao de Longo Prazo | B17: Veloso, F., Matos, S. & Peruchetti, P. | C17: 2020 | D17: 5 | E17: No | F17: Paper (results note) | G17: #brazil_productivity_and_potential_growth | H17: The companion results note — presents the actual annual Brazilian TFP series from 1981, finding average TFP growth of only 0.3%/year over 1981-2019, with a negative -0.1%/year in 2010-2019 that diverges sharply from labor productivity per hour (+0.4%/year same period) — precisely the kind of concrete, decade-by-decade breakdown (1981-90, 90-00, 00-10, 10-19) useful for a Brazil growth narrative | I17: Suggested file: ptf_brasil_visao_longo_prazo (Veloso, Matos & Peruchetti, 2020b).pdf
A18: Observatorio da Produtividade Regis Bonelli | B18: FGV/IBRE | C18: n/a | E18: No | F18: Primary source (recurring) | G18: #brazil_productivity_and_potential_growth | H18: The Observatorio da Produtividade Regis Bonelli (ibre.fgv.br/observatorio-produtividade), FGV/IBRE's dedicated productivity-tracking portal - publishes the annual TFP and labor-productivity series above on an ongoing basis, plus further reports/notes (e.g. Veloso, Matos & Peruchetti's companion piece specifically on labor productivity as the long-run growth engine). Treat similarly to CODACE in cluster 6: an ongoing feed to monitor, not a one-time acquisition.
A19: Resuscitating Real Business Cycles | B19: King, R. & Rebelo, S. | C19: 1999 | D19: 4 | E19: No | F19: Paper (handbook chapter) | G19: #modern_dsge_business_cycles | H19: Standard survey/defense/critique of the pure RBC program after a decade of challenges - the natural bridge chapter between cluster 1's founding papers and the hybrid RBC-plus-nominal-rigidity models below
A20: Nominal Rigidities and the Dynamic Effects of a Shock to Monetary Policy | B20: Christiano, L., Eichenbaum, M. & Evans, C. | C20: 2005 | D20: 5 | E20: No | F20: Paper | G20: #modern_dsge_business_cycles | H20: The "CEE model" - habit formation, investment adjustment costs, variable capital utilization, and Calvo pricing combined into the workhorse medium-scale DSGE framework most later estimated models (including Smets-Wouters below) build on
A21: Shocks and Frictions in US Business Cycles: A Bayesian DSGE Approach | B21: Smets, F. & Wouters, R. | C21: 2007 | D21: 5 | E21: No | F21: Paper | G21: #modern_dsge_business_cycles | H21: THE estimated DSGE model - the direct template for the "small-scale semi-structural models" BCB itself runs and periodically updates (see the RPM box "Atualizacao dos modelos semiestruturais de pequeno porte," June 2024) to jointly project output and inflation
A22: A Contribution to the Theory of Economic Growth | B22: Solow, R. | C22: 1956 | D22: 5 | E22: No | F22: Paper | G22: #growth_theory_neoclassical_and_endogenous | H22: THE founding neoclassical growth model - diminishing returns to capital accumulation implies growth converges to a rate set by technology and population growth alone, not savings; still the baseline every later growth model is measured against
A23: Economic Growth and Capital Accumulation | B23: Swan, T. | C23: 1956 | D23: 4 | E23: No | F23: Paper | G23: #growth_theory_neoclassical_and_endogenous | H23: Independent co-discoverer of the same model, published the same year - conventionally cited alongside Solow ("the Solow-Swan model")
A24: Optimum Growth in an Aggregative Model of Capital Accumulation | B24: Cass, D. | C24: 1965 | D24: 4 | E24: No | F24: Paper | G24: #growth_theory_neoclassical_and_endogenous | H24: Endogenizes the savings rate via intertemporal utility maximization (with Ramsey 1928 and Koopmans 1965) - the "Ramsey-Cass-Koopmans" model, the standard optimal-growth extension of Solow still taught in every graduate macro sequence
A25: Increasing Returns and Long-Run Growth | B25: Romer, P. | C25: 1986 | D25: 5 | E25: No | F25: Paper | G25: #growth_theory_neoclassical_and_endogenous | H25: The founding endogenous growth paper - knowledge/technology as an input with increasing returns, breaking Solow's diminishing-returns conclusion and making sustained growth from investment/R&D possible in the model itself
A26: On the Mechanics of Economic Development | B26: Lucas, R. | C26: 1988 | D26: 5 | E26: No | F26: Paper | G26: #growth_theory_neoclassical_and_endogenous | H26: The other founding endogenous growth paper - human capital accumulation as the engine of sustained growth, and the paper that popularized asking "why doesn't capital flow from rich to poor countries" (directly setting up cluster 4)
A27: Economic Growth (2nd ed., selected chapters) | B27: Barro, R. & Sala-i-Martin, X. | C27: 2004 | D27: 5 | E27: No | F27: Book | G27: #growth_theory_neoclassical_and_endogenous | H27: The standard graduate growth textbook. Recommended: Ch. 1-2 (Solow model and its empirical fit) plus the endogenous growth chapters (Ch. 4-5) - confirm exact chapter numbers against the table of contents on acquisition
A28: Economic Growth in a Cross Section of Countries | B28: Barro, R. | C28: 1991 | D28: 5 | E28: No | F28: Paper | G28: #convergence_middle_income_trap_and_em_growth | H28: The founding cross-country growth regression - establishes "conditional convergence" (poorer countries grow faster only after controlling for human capital, institutions, etc.) as the standard empirical framework for comparing growth across countries
A29: Divergence, Big Time | B29: Pritchett, L. | C29: 1997 | D29: 5 | E29: No | F29: Paper | G29: #convergence_middle_income_trap_and_em_growth | H29: The essential counterpoint to naive convergence optimism - documents that the dominant historical pattern across the last century is divergence in absolute income levels, not convergence; a necessary corrective before reading any convergence-framed argument about Brazil
A30: When Fast-Growing Economies Slow Down: International Evidence and Implications for China | B30: Eichengreen, B., Park, D. & Shin, K. | C30: 2012 | D30: 4 | E30: No | F30: Paper | G30: #convergence_middle_income_trap_and_em_growth | H30: The empirical middle-income-trap/growth-slowdown paper - identifies the income level and conditions under which fast-growing economies systematically decelerate, directly applicable to reading Brazil's own post-2010 growth deceleration
... A36: Incerteza e Atividade Economica | B36: Banco Central do Brasil | C36: 2019 | D36: 3 | E36: No | F36: Paper (report box / special study) | G36: #business_cycle_dating_and_coincident_indicators | H36: Applies the Baker, Bloom & Davis (2016) economic policy uncertainty methodology to Brazilian data, estimating how uncertainty shocks delay consumption/investment/employment decisions - a distinct driver-side complement to the composite indicators above, not itself a coincident/leading index
A37: CODACE - Comite de Datacao de Ciclos Economicos | B37: FGV/IBRE | C37: n/a | E37: No | F37: Primary source (recurring) | G37: #business_cycle_dating_and_coincident_indicators | H37: Ongoing primary source, not a single paper: Comite de Datacao de Ciclos Economicos (CODACE), maintained by FGV/IBRE - Brazil's own NBER-style business cycle dating committee, publishing recession/expansion turning-point calls and methodology notes on an ongoing basis rather than a fixed calendar (unlike COPOM's ~8/year cadence in the monetary policy bibliography's SS8). Retention window and ingestion approach not yet decided - flagged here rather than left undocumented, following the precedent set for COPOM materials.
A38: Indice de Atividade Economica do Banco Central (IBC-Br) | B38: Banco Central do Brasil | C38: 2010 | D38: 5 | E38: No | F38: Paper (report box) | G38: #brazil_activity_measurement | H38: IBC-Br's original launch methodology - built specifically because Brazil, unlike most economies with monthly industrial-production data, lacked any single monthly aggregate activity gauge before this
A39: Indice de Atividade Economica do Banco Central (IBC-Br) - Revisao Metodologica | B39: Banco Central do Brasil | C39: 2016 | D39: 4 | E39: No | F39: Paper (report box) | G39: #brazil_activity_measurement | H39: First major methodology revision to IBC-Br since launch - necessary to understand before comparing pre-2016 and post-2016 IBC-Br readings
A40: Aspectos Metodologicos e Comparacoes dos Comportamentos do IBC-Br e do PIB | B40: Banco Central do Brasil | C40: 2018 | D40: 4 | E40: No | F40: Paper (report box / special study) | G40: #brazil_activity_measurement | H40: Directly documents where and why IBC-Br and GDP diverge (short-horizon volatility, supply-side-only construction with no demand-side balancing, seasonal-adjustment differences) - essential caveats before treating IBC-Br as a clean monthly GDP proxy
A41: Sistema de Contas Nacionais Trimestrais: Notas Metodologicas | B41: IBGE | C41: n/a | D41: 4 | E41: No | F41: Paper (official methodology note) | G41: #brazil_activity_measurement | H41: The official Quarterly National Accounts methodology that IBC-Br is itself calibrated against (per the 2018 Estudo Especial above) - the necessary baseline reference for the gdp, pim, pmc, and pms tables already in macro_brasil
A42: Booming Sector and De-Industrialisation in a Small Open Economy | B42: Corden, W.M. & Neary, J.P. | C42: 1982 | D42: 5 | E42: No | F42: Paper | G42: #commodity_cycles_dutch_disease_and_growth | H42: The founding Dutch disease model - a commodity/resource boom that appreciates the real exchange rate and reallocates resources away from tradable manufacturing, formalizing a concern raised repeatedly in Brazilian industrial-policy debates
A43: The Natural Resource Curse: A Survey | B43: Frankel, J. | C43: 2010 | D43: 4 | E43: No | F43: Paper | G43: #commodity_cycles_dutch_disease_and_growth | H43: Comprehensive survey of the resource-curse literature and its various channels (Dutch disease, volatility, institutional/political-economy effects, the "voracity effect") - situates Corden-Neary's specific mechanism within the broader debate
A44: World Shocks, World Prices, and Business Cycles: An Empirical Investigation | B44: Fernandez, A., Schmitt-Grohe, S. & Uribe, M. | C44: 2017 | D44: 4 | E44: No | F44: Paper | G44: #commodity_cycles_dutch_disease_and_growth | H44: Quantifies how much of emerging-market business cycle variance is explained by common world/commodity-price shocks versus country-specific factors - a direct empirical framework for asking how much of Brazil's own cycle is "the commodity cycle" versus domestic policy

Sheet Quant - Economic Activity
A1: Name | B1: Source | C1: Date | D1: Importance | E1: Do we have it? | F1: Category | G1: Comments
A2: Supply side — agriculture, industry (+ extractive/manufacturing/utilities/construction), services (+ commerce/transport/info-comm/finance/real estate/other/public admin) | B2: macro_brasil.atv_pib · agropecuaria, industria, ind_extrativas, ind_transformacao, eletricidade_gas_agua, construcao, servicos, comercio, transporte_correio, informacao_comunicacao, financeiras_seguros, imobiliarias, outros_servicos, adm_saude_educacao_pub | E2: Yes | F2: 1. Quarterly GDP (Contas Nacionais Trimestrais) | G2: NSA and SA
A3: Demand side — household consumption, government consumption, gross fixed capital formation, exports, imports | B3: macro_brasil.atv_pib · consumo_familias, consumo_adm_publica, fbcf, exportacao, importacao | E3: Yes | F3: 1. Quarterly GDP (Contas Nacionais Trimestrais) | G3: NSA and SA
A4: Aggregates | B4: macro_brasil.atv_pib · pib_pm, valor_adicionado, impostos_liquidos | E4: Yes | F4: 1. Quarterly GDP (Contas Nacionais Trimestrais) | G4: NSA and SA
A5: Total, and by sector (agriculture, industry, services, ex-agriculture, taxes) | B5: macro_brasil.atv_ibcbr · ibcbr_nsa/ibcbr_sa, ibcbr_agropecuaria_*, ibcbr_industria_*, ibcbr_servicos_*, ibcbr_ex_agropecuaria_*, ibcbr_impostos_* | C5: 2003 → today, NSA and SA | E5: Yes | F5: 2. IBC-Br (monthly GDP proxy)
A6: General industry, extractive industry, manufacturing | B6: macro_brasil.atv_pim · industria_geral, ind_extrativas, ind_transformacao | C6: 2002 → today, NSA and SA | E6: Yes | F6: 3. Monthly industrial production (PIM)
A7: Restricted and expanded retail totals | B7: macro_brasil.atv_pmc · comercio_restrito_total, comercio_ampliado_total | C7: NSA and SA | E7: Yes | F7: 4. Monthly retail trade (PMC)
A8: 14 retail segments (fuel, supermarkets, apparel/footwear, furniture/appliances, pharma, books, IT equipment, other personal/household, vehicles, construction materials, wholesale food) | B8: macro_brasil.atv_pmc · segment-level series (see domain/db/brasil/ibge/atv_pmc.py) | C8: NSA and SA | E8: Yes | F8: 4. Monthly retail trade (PMC)
A9: Automóveis (passenger cars) | B9: SGS 7384 | E9: No | F9: 4a. Vehicle sales/licensing (Fenabrave via BCB SGS)
A10: Comerciais leves (light commercial vehicles) | B10: SGS 7385 | E10: No | F10: 4a. Vehicle sales/licensing (Fenabrave via BCB SGS)
A11: Caminhões (trucks) | B11: SGS 7386 | E11: No | F11: 4a. Vehicle sales/licensing (Fenabrave via BCB SGS)
A12: Ônibus (buses) | B12: SGS 7387 | E12: No | F12: 4a. Vehicle sales/licensing (Fenabrave via BCB SGS)
A13: Total services, plus 4 main groups (services to families, information/communication, professional/administrative, transport/mail) and their sub-segments (lodging, food service, telecom, IT services, road/air/water transport, real estate, etc.) | B13: macro_brasil.atv_pms · servicos_total, servicos_familias, informacao_comunicacao, prof_adm_complementares, transportes_correio, plus ~20 sub-segment columns | C13: NSA and SA | E13: Yes | F13: 5. Monthly services (PMS)
A14: Broad non-financial-sector credit by instrument and institutional sector (government, corporates, households — 17 series) | B14: macro_brasil.cred_credito_amplo · see domain/db/brasil/bcb/cred_credito_amplo.py | E14: Yes | F14: 10. Credit (activity/financial-conditions input, owned but cross-referenced) | G14: Owned by this agent — credit growth/impulse is a standard leading/coincident activity signal, not primarily a monetary-policy series despite living alongside monetary-policy-relevant data
A15: Household debt-to-income, interest burden, debt-service burden (interest + amortization) as % of income | B15: macro_brasil.cred_credito_familias · 3 series, see domain/db/brasil/bcb/cred_credito_familias.py | E15: Yes | F15: 11. Household financial conditions (context, partially owned)
A16: No output gap / potential output estimate computed — methodology now available (bibliography cluster 5), purely an implementation gap | D16: High | E16: No | F16: 6. Output gap and potential growth | G16: No output gap or potential-output series is computed anywhere in the database — this is the same gap already flagged in monetary_policy_data_inventory.md §4 ("no neutral/equilibrium real rate... no output gap") from the monetary policy side. What's changed since that inventory was written: the methodology is no longer missing — economic_activity_bibliography_candidates.md cluster 5 now has both the general toolkit (HP filter, Blanchard-Quah SVAR, Kuttner unobserved-components) and two Brazil-specific applications (Cusinato-Minella-Pôrto Júnior 2010, BCB WP 203; Souza Júnior 2005, IPEA TD 1130) with real, replicable methodology. The blocker is now purely implementation — computing any of these against macro_brasil.atv_pib (§1) and/or atv_ibcbr (§2), which are already sufficient inputs. Recommended starting point: the HP filter is the cheapest to implement and the most-replicated in the literature, but per Hodrick & Prescott's own paper (and its well-known end-of-sample bias) should be flagged as a first-pass estimate, not a final one — the Harvey-Clark unobserved-components approach from Cusinato et al. (2010) is more defensible but requires more implementation work.
A17: No CODACE business-cycle dating table — same class of gap as monetary policy's missing COPOM decision history | D17: High | E17: No | F17: 8. Business cycle dating (CODACE) | G17: No table records Brazil's own business-cycle turning points. This is the direct analogue of the "no COPOM decision history table" gap already flagged in monetary_policy_data_inventory.md §1 — CODACE (FGV/IBRE's dating committee, cluster 6 of the bibliography) publishes peak/trough dates on an irregular basis, and nothing here captures them as discrete, queryable events. Impact: the agent can describe the current IBC-Br/GDP trend but can't answer "how does the current slowdown compare, in depth and duration, to the last N recessions" without manually looking up CODACE's own bulletins each time. Possible approach: a small codace_ciclos table — (data_pico, data_vale, duracao_contracao_meses, duracao_expansao_meses) — sourced by periodically checking CODACE's published chronology (ibre.fgv.br). No script built yet; low data volume (a handful of cycles since CODACE's chronology starts in the 1980s) makes this cheap once someone owns the periodic check.
A18: No Brazilian TFP/productivity time series ingested — data exists (FGV/IBRE portal) but requires a scraper or manual re-entry | D18: Medium | E18: No | F18: 7. Productivity and TFP | G18: economic_activity_bibliography_candidates.md cluster 9 identifies exactly where Brazilian productivity data lives: BCB's own labor-productivity study (Estudo Especial 27/2018) is a one-off report, not an ongoing series, and FGV/IBRE's own annual TFP series (Veloso, Matos & Peruchetti, 2020a/b) is published on the Observatório da Produtividade Regis Bonelli (ibre.fgv.br/observatorio-produtividade) — a portal, not an SGS-style API. Impact: the agent cannot today track Brazilian TFP or labor productivity as a time series at all — every existing reference is a static report snapshot. Possible source: would require either (a) a lightweight scraper against the Observatório da Produtividade portal (structure and update cadence not yet investigated), or (b) manually re-entering the annual series from Veloso, Matos & Peruchetti's published tables once that source is acquired and processed. Not yet scoped either way.
A19: PMC and PMS limited to 2023 → today (script defaults) despite IBGE series going back much further | D19: Medium | E19: No | F19: 4. Monthly retail trade (PMC) | G19: Script: domain/db/brasil/ibge/atv_pmc.py. IBGE aggregados 8880/8881/8883. Gap — short history: coverage per CLAUDE.md: 2023 → today only, driven by the script's years_back=3 default. IBGE's PMC series (both restricted and expanded) go back to the late 1990s/2000s depending on the exact series — a full backfill would materially improve this table's usefulness for anything beyond the most recent cycle.
A20: No BCB Indicador de Condições Financeiras (ICF) or economic-policy-uncertainty index ingested | D20: Medium | E20: No | F20: 9. Leading/coincident composite indicators and financial conditions | G20: No Indicador de Condições Financeiras (ICF) — BCB's own daily financial-conditions leading indicator (Estudo Especial 76/2020, 26 variables across 7 groups via PCA) is published but not stored anywhere in macro_brasil.
A21: Vehicle sales/licensing (SGS 7384-7387) and vehicle-purchase credit (SGS 20673/25471/20728) not ingested — verified live codes, cheap to add, high-frequency consumer-durables leading indicator | D21: Medium | E21: No | F21: 4a. Vehicle sales/licensing (Fenabrave via BCB SGS) | G21: A confirmed, currently-active family of BCB SGS series, sourced from Fenabrave (the dealer federation) and distinct from anything already in PMC — the veiculos_motocicletas_pecas segment in macro_brasil.atv_pmc §4 tracks retail revenue for vehicle dealers, while this family tracks actual unit sales volumes by vehicle type. Vehicle sales/licensing is one of the most-watched high-frequency consumer-durables activity signals in Brazil, comparable to auto sales data in the US — checked live against the BCB SGS API on 2026-07 and all four series are current through May 2026: Related, not yet ingested — vehicle-purchase credit (ties this section to §10's credit table): Concessões de crédito com recursos livres — Pessoas físicas — Aquisição de veículos (SGS 20673) and the corresponding average interest rates for individuals (SGS 25471) and legal entities (SGS 20728) — a directly relevant credit-conditions overlay for interpreting vehicle sales moves (are sales rising because of demand, or because auto-loan rates fell). Note on discontinued predecessor codes: SGS 1381 and 1385 (an older vehicle-sales series pair) return data only through December 2020 — superseded by the 7384-7387 family above; don't use them for new ingestion. Possible source: straightforward addition via the existing connectors/bcb.py SGS client, same pattern as atv_ibcbr.py or cred_credito_amplo.py — no new connector needed, just a new script (e.g. domain/db/brasil/bcb/vendas_veiculos.py) with these 7 codes (4 sales + 3 credit/rate).
A22: GDP table defaults to 2016 → today despite Contas Nacionais Trimestrais data existing since 1996 | D22: Low | E22: No | F22: 1. Quarterly GDP (Contas Nacionais Trimestrais) | G22: Coverage per CLAUDE.md: 2016 → today. IBGE's own Contas Nacionais Trimestrais series goes back to 1996 — the ~2016 starting point is a script default (years_back), not a source limitation, so a full-history backfill (periodos="all") is a low-effort extension, same pattern as the ~36-month rolling windows flagged repeatedly in the other three inventories.
A23: PIM ingests only the 3 top-level categories, not the use-based or CNAE-division breakdowns IBGE also publishes | D23: Low | E23: No | F23: 3. Monthly industrial production (PIM) | G23: Script: domain/db/brasil/ibge/atv_pim.py. IBGE aggregado 8888. Gap: only the 3 highest-level categories are ingested — IBGE's PIM also publishes by broad sectoral/use-based category (capital goods, intermediate goods, durable/semi-durable/non-durable consumer goods) and by specific industrial sector (CNAE divisions), neither of which is captured here. This is the PIM-side equivalent of the disaggregation IPCA already has in the inflation agent's inventory — useful for identifying which part of industry is driving a given month's move, not just the aggregate.
A24: No credit impulse measure computed from the raw cred_credito_amplo series | D24: Low | E24: No | F24: 10. Credit (activity/financial-conditions input, owned but cross-referenced) | G24: Gap: no credit impulse measure computed (the change in new credit flow as a share of GDP, the standard "credit impulse" concept from the financial-accelerator literature already in monetary policy's bibliography) — only the raw stock/flow series exist today.
A25: No replication of the Duarte-Issler-Spacov coincident/leading index methodology | D25: Low | E25: No | F25: 9. Leading/coincident composite indicators and financial conditions | G25: No replication of the Duarte-Issler-Spacov (2004) coincident/leading index methodology.
A26: No economic policy uncertainty index for Brazil (Estudo Especial 65/2019's Baker-Bloom-Davis-style methodology) | E26: No | F26: 9. Leading/coincident composite indicators and financial conditions | G26: No economic policy uncertainty index for Brazil (Estudo Especial 65/2019's Baker-Bloom-Davis-style methodology) — not ingested.
A27: Hours worked / employment-rate / participation-rate decomposition — the "hours worked" half of the standard potential-gr | E27: Needs agent | F27: Tier 2 — From a future labor market agent (the split the user is actively considering) | G27: Hours worked / employment-rate / participation-rate decomposition — the "hours worked" half of the standard potential-growth decomposition (potential growth = labor productivity growth + hours-worked growth) referenced in BCB's own June 2024 RPM chapter on growth projections. Without this, cluster 9's productivity work (§7) can be computed but can't be combined into a full potential-growth read.
A28: Unemployment gap / NAIRU-type estimate — the labor-market-side companion to this agent's own output gap | E28: Needs agent | F28: Tier 2 — From a future labor market agent (the split the user is actively considering) | G28: Unemployment gap / NAIRU-type estimate — the labor-market-side companion to this agent's own output gap (§6); the two are usually estimated jointly or at least cross-checked against each other.
A29: Wage growth and wage bill — already sitting in macro_brasil.mt_pnad today | E29: Needs agent | F29: Tier 2 — From a future labor market agent (the split the user is actively considering) | G29: Wage growth and wage bill — already sitting in macro_brasil.mt_pnad today (per inflation_data_inventory.md §6, which documents the same table from the wage-price-spiral angle) — usable by this agent too without new ingestion, once formally scoped as a labor-agent-owned, activity-agent-consumed series.
A30: Government investment execution pace and fiscal impulse — needed to properly interpret the consumo_adm_publica and publi | E30: Needs agent | F30: Tier 2 — From a future fiscal agent | G30: Government investment execution pace and fiscal impulse — needed to properly interpret the consumo_adm_publica and public-investment components already owned in macro_brasil.atv_pib §1; today those series exist but there's no read on whether a given move is discretionary policy or automatic/base-effect.
A31: REER | E31: Needs agent | F31: Tier 2 — From the exchange rate agent (substantially built already) | G31: REER (macro_international.cmb_reer) and terms of trade (macro_brasil.cmb_termos_troca) already exist and are directly usable for bibliography cluster 8's Dutch-disease/commodity-cycle work without waiting on any new agent — flagged here only so the cross-reference is explicit, mirroring how inflation_data_inventory.md treats the same two tables.
A32: Commodity price indices — same gap already flagged in inflation_data_inventory.md's Tier 2 section; relevant here for th | E32: Needs agent | F32: Tier 2 — From a possible future global/markets agent (not yet scoped at all) | G32: Commodity price indices — same gap already flagged in inflation_data_inventory.md's Tier 2 section; relevant here for the Fernández-Schmitt-Grohé-Uribe (2017) "how much of the cycle is the world commodity cycle" framework in bibliography cluster 8.
A33: A common World/EM business-cycle factor | E33: Needs agent | F33: Tier 2 — From a possible future global/markets agent (not yet scoped at all) | G33: A common World/EM business-cycle factor (à la Fernández, Schmitt-Grohé & Uribe) — no domestic or international proxy exists in the database today.

Sheet Qual - Fiscal Policy
A1: Name | B1: Autor/Company | C1: Date | D1: Importance (1-5) | E1: Do we have it? | F1: Type | G1: Cluster | H1: Why | I1: Comments | J1: File | K1: Ingestion | L1: Ingested on | M1: Extraction | N1: QC flags | O1: Synthesis | P1: Ingestion note
A2: The 'Burden of the Debt' and the National Income | B2: Domar, E. | C2: 1944 | D2: 5 | E2: No | F2: Paper | G2: #public_debt_sustainability_and_dynamics | H2: The founding debt-sustainability arithmetic — shows that whether debt-to-GDP stabilizes or explodes depends on the relationship between the interest rate, the growth rate, and the primary balance (the "r vs. g" comparison every later debt-sustainability discussion, including Blanchard 2019 below, still uses) | I2: Suggested file: burden_of_the_debt (Domar, 1944).pdf
A3: The Behavior of U.S. Public Debt and Deficits | B3: Bohn, H. | C3: 1998 | D3: 5 | E3: No | F3: Paper | G3: #public_debt_sustainability_and_dynamics | H3: The standard empirical test for fiscal sustainability — does the primary balance respond positively to the debt level (a "fiscal reaction function")? This test, or a close variant, is the workhorse approach for asking "is a given country's fiscal stance sustainable" empirically rather than just via the r-vs-g arithmetic | I3: Suggested file: behavior_us_public_debt_deficits (Bohn, 1998).pdf
A4: Public Debt and Low Interest Rates | B4: Blanchard, O. | C4: 2019 | D4: 5 | E4: No | F4: Paper | G4: #public_debt_sustainability_and_dynamics | H4: The most influential recent re-litigation of whether high public debt is dangerous — argues that when safe rates run persistently below growth (r < g), debt rollover without future tax increases is feasible and may carry no fiscal cost, while still flagging welfare costs from reduced capital accumulation and multiple-equilibria risk (investors believing debt is risky can make it so). Essential background for reading any "is Brazil's debt sustainable" argument that invokes r vs. g | I4: Suggested file: public_debt_low_interest_rates (Blanchard, 2019).pdf
A5: An Empirical Characterization of the Dynamic Effects of Changes in Government Spending and Taxes on Output | B5: Blanchard, O. & Perotti, R. | C5: 2002 | D5: 5 | E5: No | F5: Paper | G5: #fiscal_multipliers | H5: The standard modern empirical identification strategy for fiscal shocks (SVAR with institutional/timing restrictions) — the direct methodological ancestor of almost every later fiscal multiplier estimate, including for Brazil | I5: Suggested file: empirical_characterization_fiscal_shocks (Blanchard & Perotti, 2002).pdf
A6: Can Government Purchases Stimulate the Economy? | B6: Ramey, V. | C6: 2011 | D6: 5 | E6: No | F6: Paper | G6: #fiscal_multipliers | H6: The definitive survey of the multiplier debate post-2008 — surveys the wide range of multiplier estimates across methodologies and explains why they differ so much, essential context before citing any single multiplier number | I6: Suggested file: can_government_purchases_stimulate_economy (Ramey, 2011).pdf
A7: Measuring the Output Responses to Fiscal Policy | B7: Auerbach, A. & Gorodnichenko, Y. | C7: 2012 | D7: 5 | E7: No | F7: Paper | G7: #fiscal_multipliers | H7: Shows fiscal multipliers are state-dependent — much larger during recessions/output-gap-negative periods than expansions — directly linking multiplier size to the output-gap measurement economic activity's bibliography owns, and a first-order consideration for judging any Brazilian fiscal-stimulus-timing debate | I7: Suggested file: measuring_output_responses_fiscal_policy (Auerbach & Gorodnichenko, 2012).pdf
A8: Fiscal Policy Rules | B8: Kopits, G. & Symansky, S. | C8: 1998 | D8: 5 | E8: No | F8: Paper | G8: #fiscal_rules_and_institutions | H8: The foundational typology of fiscal rules (balanced-budget rules, debt rules, expenditure rules, revenue rules) and the design criteria (well-defined, transparent, adequate, consistent, simple, flexible, enforceable) still used to evaluate any specific country's rule, including Brazil's own | I8: Suggested file: fiscal_policy_rules_typology (Kopits & Symansky, 1998).pdf
A9: Lei Complementar no 101/2000 (Lei de Responsabilidade Fiscal - LRF) | B9: Brasil | C9: 2000 | D9: 5 | E9: No | F9: Primary legal source | G9: #fiscal_rules_and_institutions | H9: Brazil's founding fiscal-institutions law — spending limits, debt limits, and transparency/reporting requirements binding on all three levels of government (Union, states, municipalities). The essential institutional backdrop for cluster 6's subnational debt material and for reading any Brazilian fiscal-rule compliance discussion since 2000 | I9: Suggested file: lei_responsabilidade_fiscal (Brasil, 2000).pdf
A10: Emenda Constitucional no 95/2016 (Novo Regime Fiscal - 'Teto de Gastos') | B10: Brasil | C10: 2016 | D10: 5 | E10: No | F10: Primary legal source | G10: #fiscal_rules_and_institutions | H10: The constitutional spending cap that governed federal fiscal policy from 2017 until its 2023 replacement — capped real primary expenditure growth near zero, became the dominant fiscal-anchor framing (and the dominant target of criticism) for that period | I10: Suggested file: teto_de_gastos_ec95 (Brasil, 2016).pdf
A11: Lei Complementar no 200/2023 (Novo Arcabouco Fiscal) | B11: Brasil | C11: 2023 | D11: 5 | E11: No | F11: Primary legal source | G11: #fiscal_rules_and_institutions | H11: The spending cap's replacement — combines a real-expenditure-growth band (0.6%-2.5%/year) with an annually-set primary-result target defined in the budget guidelines law (LDO), a materially different design logic (band + target vs. Teto de Gastos's near-fixed ceiling) | I11: Suggested file: novo_arcabouco_fiscal_lc200 (Brasil, 2023).pdf
A12: Novo Arcabouco Tenta Equilibrar Sustentabilidade Fiscal e Racionalidade Tributaria | B12: Instituto Brasileiro de Economia (IBRE/FGV) | C12: 2023 | D12: 3 | E12: No | F12: Paper (institutional commentary) | G12: #fiscal_rules_and_institutions | H12: Contemporary independent assessment of the new framework's design tradeoffs — individual author not identified in this pass (published as an institutional "Carta do IBRE," not individually bylined); useful as a practitioner-level complement to the primary legal text above, not a substitute for a peer-reviewed academic assessment, which hasn't been identified yet given the framework's recency | I12: Suggested file: novo_arcabouco_avaliacao_ibre (IBRE/FGV, 2023).pdf
A13: Debt Intolerance | B13: Reinhart, C., Rogoff, K. & Savastano, M. | C13: 2003 | D13: 5 | E13: No | F13: Paper | G13: #fiscal_capacity_debt_intolerance_and_dominance | H13: The founding statement of "debt intolerance" — many emerging markets face default risk and loss of market access at debt-to-GDP levels far below what advanced economies routinely sustain, because of a history of default and weaker institutional credibility, not the debt ratio alone. Essential framing for any argument about "how much debt can Brazil actually carry" that isn't just Domar/Blanchard arithmetic transplanted from a reserve-currency context | I13: Suggested file: debt_intolerance (Reinhart, Rogoff & Savastano, 2003).pdf
... A18: Hamilton's Paradox: The Promise and Peril of Fiscal Federalism | B18: Rodden, J. | C18: 2006 | D18: 5 | E18: No | F18: Book | G18: #brazil_fiscal_federalism_and_subnational_debt | H18: The standard modern cross-country treatment of the subnational-bailout problem — federal governments that repeatedly bail out over-indebted states/provinces create exactly the moral hazard that produces the next bailout; Brazil is one of the book's central comparative cases (alongside Argentina, Germany, the US), directly relevant to the 1990s state-debt crises that motivated the LRF (cluster 3) and to recurring pressure from individual states (e.g. Rio de Janeiro) since | I18: Suggested file: hamiltons_paradox_selected_chapters (Rodden, 2006).pdf
A19: Fiscal Policy in Latin America | B19: Gavin, M. & Perotti, R. | C19: 1997 | D19: 5 | E19: No | F19: Paper | G19: #latin_america_regional_fiscal_policy | H19: The foundational finding: fiscal policy across 13 major Latin American economies is procyclical (expansionary in booms, contractionary in busts) - the opposite of the countercyclical pattern textbook theory recommends and industrial economies broadly display. Built on a purpose-collected database covering central government, local government, and non-financial public enterprises across the region
A20: Has Fiscal Policy Become Less Procyclical in Latin America? (Chapter 7 in Latin America, IMF) | B20: Klemm, A. | C20: n/a | D20: 4 | E20: No | F20: Paper (book chapter) | G20: #latin_america_regional_fiscal_policy | H20: The natural modern re-test of Gavin & Perotti's 1997 finding - asks whether two more decades of fiscal-rule adoption and institutional reform across the region (directly relevant to cluster 3's Brazil-specific rule history and cluster 6's federalism material) actually reduced procyclicality, or whether the pattern persisted
A21: Fiscal dominance | B21: itau | C21: 2025 | E21: Yes | I21: Added by ingestion: not in the curated list. Fill in columns A-I and delete this sentence to keep the row. | J21: fiscal_dominance (itau, 2025) | K21: Ingested | L21: 2026-10-20 | M21: reclean (cleaner change) | O21: Yes

Sheet Quant - Fiscal Policy
A1: Name | B1: Source | C1: Date | D1: Importance | E1: Do we have it? | F1: Category | G1: Comments
A2: Dívida Bruta do Governo Geral (DBGG) — % GDP | B2: SGS 13762 | E2: No | F2: 1. Public debt stock | G2: gross debt, general government, current methodology (post-2008)
A3: Dívida Líquida do Setor Público (DLSP) — % GDP, total (federal government + central bank) | B3: SGS 4503 | E3: No | F3: 1. Public debt stock
A4: Dívida líquida do governo geral — % GDP | B4: SGS 4536 | E4: No | F4: 1. Public debt stock | G4: narrower institutional scope than 4503 (excludes public enterprises/state-level nuances captured elsewhere)
A5: Dívida Líquida do Setor Público — R$ million, total, consolidated public sector | B5: SGS 4478 | E5: No | F5: 1. Public debt stock | G5: the level series behind the ratio series above — useful for reconciling with nominal GDP independently rather than trusting BCB's own ratio calculation
A6: NFSP sem desvalorização cambial — Resultado primário, % GDP, 12-month accumulated flow, consolidated public sector | B6: SGS 5793 | E6: No | F6: 2. Fiscal balance (primary and nominal result) | G6: the standard "primary result" headline figure
A7: NFSP sem desvalorização cambial — Resultado nominal, % GDP, 12-month accumulated flow, consolidated public sector | B7: SGS 5727 | E7: No | F7: 2. Fiscal balance (primary and nominal result) | G7: primary result plus net interest payments — the figure that actually determines whether debt-to-GDP (§1) is rising or falling, given Domar's arithmetic (bibliography cluster 1)
A8: NFSP sem desvalorização cambial — Resultado primário, current monthly flow, R$ million, consolidated public sector | B8: SGS 4649 | E8: No | F8: 2. Fiscal balance (primary and nominal result) | G8: the monthly (not 12m-smoothed) series — needed for anything higher-frequency than the standard 12m headline read, e.g. seasonal patterns in tax collection/spending
A9: No public debt stock series at all (gross and net) — verified SGS codes identified, purely an implementation gap | D9: High | E9: No | F9: 1. Public debt stock | G9: All four confirmed live against the BCB SGS API (2026-07), current through May 2026. This is the single most foundational gap in this inventory — bibliography cluster 1 (debt sustainability arithmetic) and cluster 4 (debt intolerance) are both unusable for Brazil without a debt-stock series, and monetary policy's, inflation's, and economic activity's inventories all already list "a primary-balance/debt-trajectory signal" as a Tier 2 dependency on this agent. Gap within the gap: DBGG (gross) and DLSP (net) are conceptually different and shouldn't be used interchangeably — gross debt doesn't net out financial assets (like BCB's own international reserves) the way net debt does, and international debt-sustainability comparisons (including Reinhart-Rogoff-Savastano's debt-intolerance thresholds, bibliography cluster 4) are usually framed in gross terms while Brazil's own domestic commentary has historically emphasized net debt — both should be ingested rather than picking one.
A10: No fiscal balance series at all (primary and nominal result) — verified SGS codes identified, purely an implementation gap | D10: High | E10: No | F10: 2. Fiscal balance (primary and nominal result) | G10: All three confirmed live (2026-07). "NFSP" = Necessidades de Financiamento do Setor Público, BCB's own public-sector-borrowing-requirement framework — "sem desvalorização cambial" means the exchange-rate-valuation effect on FX-denominated debt is stripped out, giving a cleaner read on the actual fiscal effort rather than a currency-move artifact. Gap within the gap: BCB's "setor público consolidado" (consolidated public sector, the scope of all series above) bundles federal government, states, municipalities, and state-owned enterprises together — there is no breakdown by government level in what's ingested so far, which matters directly for bibliography cluster 6 (subnational federalism). Separately, Tesouro Nacional's own monthly "Resultado do Tesouro Nacional" and "Resultado Primário do Governo Central" releases are methodologically distinct from BCB's SGS figures (different institutional scope — central government only, not the full consolidated public sector) and are the more commonly-cited headline number in Brazilian financial-press coverage; whether Tesouro publishes this as its own SGS-accessible series or only via its own portal (Tesouro Transparente) wasn't confirmed in this pass.
A11: No revenue/expenditure breakdown by type or function — no source confirmed yet, needs investigation beyond SGS | D11: Medium | E11: No | F11: 3. Government revenue and expenditure breakdown | G11: No series for tax revenue (by type — IRPF, IRPJ, COFINS, ICMS et al.) or expenditure (by function — Previdência, saúde, educação, custeio vs. investimento) was identified in this pass. This is a materially bigger gap than §1-§2: debt and the aggregate balance answer "how much and is it rising," but nothing here yet answers "why" — which specific revenue or spending line is driving a given month's fiscal outcome. Possible source: likely Tesouro Nacional's own RREO (Relatório Resumido de Execução Orçamentária, monthly-ish) and RGF (Relatório de Gestão Fiscal, quarterly) releases, or the SIAFI/Tesouro Transparente portal directly — none of these were investigated for API accessibility in this pass, unlike the SGS-based series in §1-§2 which are confirmed straightforward.
A12: No fiscal rule compliance table (Teto de Gastos historical, Novo Arcabouço target/band vs. actual) | D12: Medium | E12: No | F12: 5. Fiscal rule compliance metrics (Teto de Gastos / Novo Arcabouço Fiscal) | G12: Neither the historical Teto de Gastos (EC 95/2016) ceiling levels nor the current Novo Arcabouço Fiscal's (LC 200/2023) expense-growth band (0.6%-2.5% real) and annually-set primary-result target (set via the LDO, per bibliography cluster 3) are tracked anywhere. Unlike §1-§2, this is very unlikely to be an SGS series — it's a small number of administratively-set parameters that change on a predictable (annual, for the LDO target) or rare (constitutional-amendment-level, for a rule replacement) cadence. Recommended approach: a small lookup table — (ano, meta_resultado_primario, banda_crescimento_despesa_min, banda_crescimento_despesa_max, regra_vigente) — maintained by periodically checking the LDO and any rule amendments, the same "small, slow-moving, cheap once someone owns it" pattern already used for the proposed inflation-target-parameters table in monetary_policy_data_inventory.md §6 and the proposed minimum-wage table in labor_market_data_inventory.md §7. Why this matters beyond bookkeeping: without it, the agent can report the primary result (§2) but can't say whether it's compliant with the rule currently in force — the entire point of a fiscal rule, per bibliography cluster 3's Kopits & Symansky framework, is that it's a benchmark to be measured against, not just a number to report in isolation.
A13: No subnational (state/municipality) debt or fiscal result breakdown | D13: Medium | E13: No | F13: 6. Subnational (states and municipalities) debt and fiscal result | G13: Bibliography cluster 6 (federalism/subnational debt, built around Rodden's Hamilton's Paradox) has no matching data — §1-§2's series are all consolidated-public-sector aggregates with no state/municipality-level breakdown. Given Rio de Janeiro's 2016-17 fiscal crisis is one of the bibliography's own flagged open gaps (a citation, not just data), this is a case where the literature and data gaps reinforce each other and are worth closing together. Possible source: BCB SGS does publish some subnational-level debt series (state-level DLSP breakdowns) — not confirmed via live check in this pass, unlike §1-§2; STN (Secretaria do Tesouro Nacional) also publishes state-level fiscal data directly. Needs a dedicated verification pass before building.
A14: No RGPS/Previdência-specific deficit series isolated from the broader expenditure breakdown | D14: Low | E14: No | F14: 4. Pension/social security balance (RGPS deficit) | G14: Bibliography cluster 5 identifies pension spending as the dominant driver of Brazil's structural primary-spending growth, but no series specifically isolating the RGPS (Regime Geral de Previdência Social) actuarial or cash-flow deficit was identified or confirmed via SGS in this pass — this would sit inside §3's broader expenditure-by-function breakdown rather than as its own standalone series, but is flagged separately given how load-bearing it is for reading EC 103/2019's (2019 pension reform) actual realized effect, the same open gap already flagged in the bibliography file itself.
A15: Tesouro Nacional's own central-government-only result release not reconciled against BCB's consolidated-public-sector series | D15: Low | E15: No | F15: 2. Fiscal balance (primary and nominal result) | G15: All three confirmed live (2026-07). "NFSP" = Necessidades de Financiamento do Setor Público, BCB's own public-sector-borrowing-requirement framework — "sem desvalorização cambial" means the exchange-rate-valuation effect on FX-denominated debt is stripped out, giving a cleaner read on the actual fiscal effort rather than a currency-move artifact. Gap within the gap: BCB's "setor público consolidado" (consolidated public sector, the scope of all series above) bundles federal government, states, municipalities, and state-owned enterprises together — there is no breakdown by government level in what's ingested so far, which matters directly for bibliography cluster 6 (subnational federalism). Separately, Tesouro Nacional's own monthly "Resultado do Tesouro Nacional" and "Resultado Primário do Governo Central" releases are methodologically distinct from BCB's SGS figures (different institutional scope — central government only, not the full consolidated public sector) and are the more commonly-cited headline number in Brazilian financial-press coverage; whether Tesouro publishes this as its own SGS-accessible series or only via its own portal (Tesouro Transparente) wasn't confirmed in this pass.
A16: Output gap / potential output estimate — needed to compute a cyclically-adjusted | E16: Needs agent | F16: Tier 2 — From the economic activity agent | G16: Output gap / potential output estimate — needed to compute a cyclically-adjusted (structural) primary balance, the standard way of separating a genuine fiscal policy stance change from an automatic, cycle-driven revenue/spending swing. Flagged as a gap in economic_activity_data_inventory.md §6 itself — this agent inherits that same gap rather than duplicating it.
A17: Nominal GDP — needed as the denominator for every ratio series in §1-§2 above; macro_brasil.atv_pib already has this | E17: Needs agent | F17: Tier 2 — From the economic activity agent | G17: Nominal GDP — needed as the denominator for every ratio series in §1-§2 above; macro_brasil.atv_pib already has this (owned by economic activity), so this is a straightforward existing dependency rather than a placeholder.
A18: A sovereign risk premium proxy | E18: Needs agent | F18: Tier 2 — From the exchange rate agent | G18: A sovereign risk premium proxy (EMBI-style spread, or CDS) — the market-priced complement to Reinhart-Rogoff-Savastano's debt-intolerance framing (bibliography cluster 4): does the market currently treat Brazil's debt level as risky, independent of what the arithmetic alone would say? Not currently identified as existing in exchange_rate_data_inventory.md either — a gap shared across two agents' inventories rather than resolved in either.
A19: The real interest rate path | E19: Needs agent | F19: Tier 2 — From the monetary policy agent | G19: The real interest rate path (Selic real, already computed in macro_international.diferenciais_juros) — needed to project debt-service costs and to interpret the r-vs-g comparison (Domar 1944 / Blanchard 2019, bibliography cluster 1) using Brazil's actual, not a generic, r.
A20: The minimum wage series and Previdência indexation rule itself, once built there | E20: Needs agent | F20: Tier 2 — From the labor market agent | G20: The minimum wage series and Previdência indexation rule itself, once built there (§7 above) — restated as a forward pointer rather than a fresh placeholder.

Sheet Qual - Inflation
A1: Name | B1: Autor/Company | C1: Date | D1: Importance (1-5) | E1: Do we have it? | F1: Type | G1: Cluster | H1: Why | I1: Comments | J1: File | K1: Ingestion | L1: Ingested on | M1: Extraction | N1: QC flags | O1: Synthesis | P1: Ingestion note
A2: The Relation between Unemployment and the Rate of Change of Money Wage Rates in the United Kingdom, 1861-1957 | B2: Phillips, A.W. | C2: 1958 | D2: 5 | E2: No | F2: Paper | G2: #phillips_curve_and_expectations_augmentation | H2: The original empirical curve — starting point for the entire literature, including its own eventual refutation | I2: Suggested file: original_phillips_curve (Phillips, 1958).pdf
A3: Phillips Curves, Expectations of Inflation and Optimal Unemployment over Time | B3: Phelps, E. | C3: 1967 | D3: 5 | E3: No | F3: Paper | G3: #phillips_curve_and_expectations_augmentation | H3: Co-discoverer (with Friedman) of the expectations-augmented Phillips curve and the natural rate concept - the theoretical rupture that made the original curve's apparent policy trade-off illusory
A4: Econometric Policy Evaluation: A Critique | B4: Lucas, R. | C4: 1976 | D4: 5 | E4: No | F4: Paper | G4: #phillips_curve_and_expectations_augmentation | H4: The Lucas critique, developed largely through the Phillips curve example - explains why the naive statistical trade-off breaks down when policy exploits it, essential background for reading any later Phillips curve work critically
A5: Inflation Dynamics: A Structural Econometric Analysis | B5: Gali, J. & Gertler, M. | C5: 1999 | D5: 5 | E5: No | F5: Paper | G5: #phillips_curve_and_expectations_augmentation | H5: The empirical New Keynesian Phillips curve (NKPC) paper - estimates the hybrid backward/forward-looking specification that remains the workhorse for inflation dynamics research; distinct from Clarida-Gali-Gertler (1999, in monetary policy), which surveys the policy-rule side rather than estimating the inflation equation itself
A6: The Phillips Curve: Back to the '60s | B6: Blanchard, O. | C6: 2016 | D6: 4 | E6: No | F6: Paper | G6: #phillips_curve_and_expectations_augmentation | H6: Documents the post-2008 flattening of the curve and argues the relationship has reverted toward its pre-1970s low-slope, low-persistence form - the direct setup for the 'missing disinflation' and 'missing inflation' puzzles below
A7: Globalisation and Inflation: New Cross-Country Evidence on the Global Determinants of Domestic Inflation | B7: Borio, C. & Filardo, A. | C7: 2007 | D7: 4 | E7: No | F7: Paper | G7: #phillips_curve_and_expectations_augmentation | H7: The structural explanation underlying much of the 2010s low-inflation commentary: argues global slack (import competition, global value chains), not domestic slack, is what disciplines prices - a leading candidate answer for why the curve looks flat from a purely domestic-variables perspective
A8: The Dog That Didn't Bark: Has Inflation Been Muzzled or Was It Just Sleeping? | B8: International Monetary Fund | C8: 2013 | D8: 4 | E8: No | F8: Paper (institutional report chapter) | G8: #phillips_curve_and_expectations_augmentation | H8: The earliest, most influential institutional statement of the missing-disinflation puzzle - argues anchored expectations explain why inflation didn't fall as much as pre-2008 models predicted despite the Great Recession's huge output gaps; predates and complements Coibion & Gorodnichenko (2015) below
A9: Prospects for Inflation in a High Pressure Economy: Is the Phillips Curve Dead or Is It Just Hibernating? | B9: Hooper, P., Mishkin, F. & Sufi, A. | C9: 2019 | D9: 5 | E9: No | F9: Paper | G9: #phillips_curve_and_expectations_augmentation | H9: The most comprehensive later verdict on the full 2008-2019 flattening episode - covers both the 2009-11 'missing disinflation' and the mirror-image 2015-19 'missing inflation' (unemployment at multi-decade lows with no inflation acceleration), concluding the curve is very flat but not dead. The single best entry point if only one source from this stretch is read
A10: Is the Phillips Curve Alive and Well After All? Inflation Expectations and the Missing Disinflation | B10: Coibion, O. & Gorodnichenko, Y. | C10: 2015 | D10: 4 | E10: No | F10: Paper | G10: #phillips_curve_and_expectations_augmentation | H10: Resolves the 2009-11 'missing disinflation' puzzle by showing standard Phillips curve estimates use the wrong expectations measure - directly bridges to cluster 2
A11: Targets and Inflation Dynamics | B11: Alves, S.A.L. & Areosa, W.D. | C11: 2005 | D11: 4 | E11: No | F11: Paper | G11: #phillips_curve_and_expectations_augmentation | H11: Derives a Brazil-specific NKPC with indexation to both past inflation and the inflation target itself, generalizing Woodford's (2003) hybrid curve - the direct Brazilian counterpart to Gali & Gertler (1999) above, built for a regime (explicit inflation targets) the original NKPC wasn't designed around
